{
  "2025-08-27 13:00:00": {
    "_processed_at": "2025-08-27T13:24:12.427064",
    "melon_top100": [
      {
        "rank": 25,
        "title": "HAPPY",
        "artist": "DAY6 (데이식스)",
        "timestamp": "2025-08-27 13:00",
        "chart_type": "TOP100"
      },
      {
        "rank": 31,
        "title": "한 페이지가 될 수 있게",
        "artist": "DAY6 (데이식스)",
        "timestamp": "2025-08-27 13:00",
        "chart_type": "TOP100"
      },
      {
        "rank": 44,
        "title": "Welcome to the Show",
        "artist": "DAY6 (데이식스)",
        "timestamp": "2025-08-27 13:00",
        "chart_type": "TOP100"
      },
      {
        "rank": 47,
        "title": "예뻤어",
        "artist": "DAY6 (데이식스)",
        "timestamp": "2025-08-27 13:00",
        "chart_type": "TOP100"
      }
    ],
    "melon_hot100": [
      {
        "rank": null,
        "timestamp": "2025-08-27 13:00:00",
        "chart_type": "HOT100"
      }
    ],
    "melon": [
      {
        "rank": 25,
        "title": "HAPPY",
        "artist": "DAY6 (데이식스)",
        "timestamp": "2025-08-27 13:00",
        "chart_type": "TOP100"
      },
      {
        "rank": 31,
        "title": "한 페이지가 될 수 있게",
        "artist": "DAY6 (데이식스)",
        "timestamp": "2025-08-27 13:00",
        "chart_type": "TOP100"
      },
      {
        "rank": 44,
        "title": "Welcome to the Show",
        "artist": "DAY6 (데이식스)",
        "timestamp": "2025-08-27 13:00",
        "chart_type": "TOP100"
      },
      {
        "rank": 47,
        "title": "예뻤어",
        "artist": "DAY6 (데이식스)",
        "timestamp": "2025-08-27 13:00",
        "chart_type": "TOP100"
      }
    ],
    "genie": [
      {
        "rank": 19,
        "title": "HAPPY",
        "artist": "DAY6 (데이식스)",
        "timestamp": "2025-08-27 13:00"
      },
      {
        "rank": 26,
        "title": "한 페이지가 될 수 있게",
        "artist": "DAY6 (데이식스)",
        "timestamp": "2025-08-27 13:00"
      },
      {
        "rank": 32,
        "title": "Welcome to the Show",
        "artist": "DAY6 (데이식스)",
        "timestamp": "2025-08-27 13:00"
      },
      {
        "rank": 41,
        "title": "예뻤어",
        "artist": "DAY6 (데이식스)",
        "timestamp": "2025-08-27 13:00"
      },
      {
        "rank": null,
        "title": "Congratulations",
        "artist": "DAY6 (데이식스)",
        "timestamp": "2025-08-27 13:00"
      }
    ],
    "bugs": [
      {
        "rank": null,
        "timestamp": "2025-08-27 13:00:00"
      }
    ],
    "vibe": [
      {
        "rank": 30,
        "title": "HAPPY",
        "artist": "DAY6(데이식스)",
        "timestamp": "2025-08-27 13:00"
      },
      {
        "rank": 32,
        "title": "한 페이지가 될 수 있게",
        "artist": "DAY6(데이식스)",
        "timestamp": "2025-08-27 13:00"
      },
      {
        "rank": 56,
        "title": "Welcome to the Show",
        "artist": "DAY6(데이식스)",
        "timestamp": "2025-08-27 13:00"
      },
      {
        "rank": 67,
        "title": "예뻤어",
        "artist": "DAY6(데이식스)",
        "timestamp": "2025-08-27 13:00"
      }
    ],
    "flo": [
      {
        "rank": 42,
        "title": "HAPPY",
        "artist": "DAY6 (데이식스)",
        "timestamp": "2025-08-27 13:00"
      },
      {
        "rank": 43,
        "title": "한 페이지가 될 수 있게",
        "artist": "DAY6 (데이식스)",
        "timestamp": "2025-08-27 13:00"
      },
      {
        "rank": 72,
        "title": "Welcome to the Show",
        "artist": "DAY6 (데이식스)",
        "timestamp": "2025-08-27 13:00"
      }
    ]
  },
  "2025-08-27 14:00:00": {
    "_processed_at": "2025-08-27T14:19:10.613840",
    "melon_top100": [
      {
        "rank": 27,
        "title": "HAPPY",
        "artist": "DAY6 (데이식스)",
        "timestamp": "2025-08-27 14:00",
        "chart_type": "TOP100"
      },
      {
        "rank": 29,
        "title": "한 페이지가 될 수 있게",
        "artist": "DAY6 (데이식스)",
        "timestamp": "2025-08-27 14:00",
        "chart_type": "TOP100"
      },
      {
        "rank": 42,
        "title": "Welcome to the Show",
        "artist": "DAY6 (데이식스)",
        "timestamp": "2025-08-27 14:00",
        "chart_type": "TOP100"
      },
      {
        "rank": 46,
        "title": "예뻤어",
        "artist": "DAY6 (데이식스)",
        "timestamp": "2025-08-27 14:00",
        "chart_type": "TOP100"
      }
    ],
    "melon_hot100": [
      {
        "rank": null,
        "timestamp": "2025-08-27 14:00:00",
        "chart_type": "HOT100"
      }
    ],
    "melon": [
      {
        "rank": 27,
        "title": "HAPPY",
        "artist": "DAY6 (데이식스)",
        "timestamp": "2025-08-27 14:00",
        "chart_type": "TOP100"
      },
      {
        "rank": 29,
        "title": "한 페이지가 될 수 있게",
        "artist": "DAY6 (데이식스)",
        "timestamp": "2025-08-27 14:00",
        "chart_type": "TOP100"
      },
      {
        "rank": 42,
        "title": "Welcome to the Show",
        "artist": "DAY6 (데이식스)",
        "timestamp": "2025-08-27 14:00",
        "chart_type": "TOP100"
      },
      {
        "rank": 46,
        "title": "예뻤어",
        "artist": "DAY6 (데이식스)",
        "timestamp": "2025-08-27 14:00",
        "chart_type": "TOP100"
      }
    ],
    "genie": [
      {
        "rank": 19,
        "title": "HAPPY",
        "artist": "DAY6 (데이식스)",
        "timestamp": "2025-08-27 14:00"
      },
      {
        "rank": 27,
        "title": "한 페이지가 될 수 있게",
        "artist": "DAY6 (데이식스)",
        "timestamp": "2025-08-27 14:00"
      },
      {
        "rank": 38,
        "title": "Welcome to the Show",
        "artist": "DAY6 (데이식스)",
        "timestamp": "2025-08-27 14:00"
      },
      {
        "rank": 39,
        "title": "예뻤어",
        "artist": "DAY6 (데이식스)",
        "timestamp": "2025-08-27 14:00"
      },
      {
        "rank": null,
        "title": "Congratulations",
        "artist": "DAY6 (데이식스)",
        "timestamp": "2025-08-27 14:00"
      }
    ],
    "bugs": [
      {
        "rank": null,
        "timestamp": "2025-08-27 14:00:00"
      }
    ],
    "vibe": [
      {
        "rank": 30,
        "title": "HAPPY",
        "artist": "DAY6(데이식스)",
        "timestamp": "2025-08-27 14:00"
      },
      {
        "rank": 32,
        "title": "한 페이지가 될 수 있게",
        "artist": "DAY6(데이식스)",
        "timestamp": "2025-08-27 14:00"
      },
      {
        "rank": 56,
        "title": "Welcome to the Show",
        "artist": "DAY6(데이식스)",
        "timestamp": "2025-08-27 14:00"
      },
      {
        "rank": 67,
        "title": "예뻤어",
        "artist": "DAY6(데이식스)",
        "timestamp": "2025-08-27 14:00"
      }
    ],
    "flo": [
      {
        "rank": 40,
        "title": "HAPPY",
        "artist": "DAY6 (데이식스)",
        "timestamp": "2025-08-27 14:00"
      },
      {
        "rank": 43,
        "title": "한 페이지가 될 수 있게",
        "artist": "DAY6 (데이식스)",
        "timestamp": "2025-08-27 14:00"
      },
      {
        "rank": 72,
        "title": "Welcome to the Show",
        "artist": "DAY6 (데이식스)",
        "timestamp": "2025-08-27 14:00"
      }
    ]
  },
  "2025-08-27 15:00:00": {
    "_processed_at": "2025-08-27T15:29:16.390087",
    "melon_top100": [
      {
        "rank": 27,
        "title": "HAPPY",
        "artist": "DAY6 (데이식스)",
        "timestamp": "2025-08-27 15:00",
        "chart_type": "TOP100"
      },
      {
        "rank": 31,
        "title": "한 페이지가 될 수 있게",
        "artist": "DAY6 (데이식스)",
        "timestamp": "2025-08-27 15:00",
        "chart_type": "TOP100"
      },
      {
        "rank": 40,
        "title": "Welcome to the Show",
        "artist": "DAY6 (데이식스)",
        "timestamp": "2025-08-27 15:00",
        "chart_type": "TOP100"
      },
      {
        "rank": 44,
        "title": "예뻤어",
        "artist": "DAY6 (데이식스)",
        "timestamp": "2025-08-27 15:00",
        "chart_type": "TOP100"
      }
    ],
    "melon_hot100": [
      {
        "rank": null,
        "timestamp": "2025-08-27 15:00:00",
        "chart_type": "HOT100"
      }
    ],
    "melon": [
      {
        "rank": 27,
        "title": "HAPPY",
        "artist": "DAY6 (데이식스)",
        "timestamp": "2025-08-27 15:00",
        "chart_type": "TOP100"
      },
      {
        "rank": 31,
        "title": "한 페이지가 될 수 있게",
        "artist": "DAY6 (데이식스)",
        "timestamp": "2025-08-27 15:00",
        "chart_type": "TOP100"
      },
      {
        "rank": 40,
        "title": "Welcome to the Show",
        "artist": "DAY6 (데이식스)",
        "timestamp": "2025-08-27 15:00",
        "chart_type": "TOP100"
      },
      {
        "rank": 44,
        "title": "예뻤어",
        "artist": "DAY6 (데이식스)",
        "timestamp": "2025-08-27 15:00",
        "chart_type": "TOP100"
      }
    ],
    "genie": [
      {
        "rank": 20,
        "title": "HAPPY",
        "artist": "DAY6 (데이식스)",
        "timestamp": "2025-08-27 15:00"
      },
      {
        "rank": 24,
        "title": "한 페이지가 될 수 있게",
        "artist": "DAY6 (데이식스)",
        "timestamp": "2025-08-27 15:00"
      },
      {
        "rank": 35,
        "title": "Welcome to the Show",
        "artist": "DAY6 (데이식스)",
        "timestamp": "2025-08-27 15:00"
      },
      {
        "rank": 39,
        "title": "예뻤어",
        "artist": "DAY6 (데이식스)",
        "timestamp": "2025-08-27 15:00"
      },
      {
        "rank": null,
        "title": "Congratulations",
        "artist": "DAY6 (데이식스)",
        "timestamp": "2025-08-27 15:00"
      }
    ],
    "bugs": [
      {
        "rank": null,
        "timestamp": "2025-08-27 15:00:00"
      }
    ],
    "vibe": [
      {
        "rank": 30,
        "title": "HAPPY",
        "artist": "DAY6(데이식스)",
        "timestamp": "2025-08-27 15:00"
      },
      {
        "rank": 32,
        "title": "한 페이지가 될 수 있게",
        "artist": "DAY6(데이식스)",
        "timestamp": "2025-08-27 15:00"
      },
      {
        "rank": 56,
        "title": "Welcome to the Show",
        "artist": "DAY6(데이식스)",
        "timestamp": "2025-08-27 15:00"
      },
      {
        "rank": 67,
        "title": "예뻤어",
        "artist": "DAY6(데이식스)",
        "timestamp": "2025-08-27 15:00"
      }
    ],
    "flo": [
      {
        "rank": 40,
        "title": "HAPPY",
        "artist": "DAY6 (데이식스)",
        "timestamp": "2025-08-27 15:00"
      },
      {
        "rank": 42,
        "title": "한 페이지가 될 수 있게",
        "artist": "DAY6 (데이식스)",
        "timestamp": "2025-08-27 15:00"
      },
      {
        "rank": 69,
        "title": "Welcome to the Show",
        "artist": "DAY6 (데이식스)",
        "timestamp": "2025-08-27 15:00"
      }
    ]
  },
  "2025-08-27 16:00:00": {
    "_processed_at": "2025-08-27T16:19:09.330400",
    "melon_top100": [
      {
        "rank": 28,
        "title": "HAPPY",
        "artist": "DAY6 (데이식스)",
        "timestamp": "2025-08-27 16:00",
        "chart_type": "TOP100"
      },
      {
        "rank": 31,
        "title": "한 페이지가 될 수 있게",
        "artist": "DAY6 (데이식스)",
        "timestamp": "2025-08-27 16:00",
        "chart_type": "TOP100"
      },
      {
        "rank": 41,
        "title": "Welcome to the Show",
        "artist": "DAY6 (데이식스)",
        "timestamp": "2025-08-27 16:00",
        "chart_type": "TOP100"
      },
      {
        "rank": 46,
        "title": "예뻤어",
        "artist": "DAY6 (데이식스)",
        "timestamp": "2025-08-27 16:00",
        "chart_type": "TOP100"
      }
    ],
    "melon_hot100": [
      {
        "rank": null,
        "timestamp": "2025-08-27 16:00:00",
        "chart_type": "HOT100"
      }
    ],
    "melon": [
      {
        "rank": 28,
        "title": "HAPPY",
        "artist": "DAY6 (데이식스)",
        "timestamp": "2025-08-27 16:00",
        "chart_type": "TOP100"
      },
      {
        "rank": 31,
        "title": "한 페이지가 될 수 있게",
        "artist": "DAY6 (데이식스)",
        "timestamp": "2025-08-27 16:00",
        "chart_type": "TOP100"
      },
      {
        "rank": 41,
        "title": "Welcome to the Show",
        "artist": "DAY6 (데이식스)",
        "timestamp": "2025-08-27 16:00",
        "chart_type": "TOP100"
      },
      {
        "rank": 46,
        "title": "예뻤어",
        "artist": "DAY6 (데이식스)",
        "timestamp": "2025-08-27 16:00",
        "chart_type": "TOP100"
      }
    ],
    "genie": [
      {
        "rank": 19,
        "title": "HAPPY",
        "artist": "DAY6 (데이식스)",
        "timestamp": "2025-08-27 16:00"
      },
      {
        "rank": 25,
        "title": "한 페이지가 될 수 있게",
        "artist": "DAY6 (데이식스)",
        "timestamp": "2025-08-27 16:00"
      },
      {
        "rank": 32,
        "title": "Welcome to the Show",
        "artist": "DAY6 (데이식스)",
        "timestamp": "2025-08-27 16:00"
      },
      {
        "rank": 39,
        "title": "예뻤어",
        "artist": "DAY6 (데이식스)",
        "timestamp": "2025-08-27 16:00"
      },
      {
        "rank": null,
        "title": "Congratulations",
        "artist": "DAY6 (데이식스)",
        "timestamp": "2025-08-27 16:00"
      }
    ],
    "bugs": [
      {
        "rank": null,
        "timestamp": "2025-08-27 16:00:00"
      }
    ],
    "vibe": [
      {
        "rank": 30,
        "title": "HAPPY",
        "artist": "DAY6(데이식스)",
        "timestamp": "2025-08-27 16:00"
      },
      {
        "rank": 32,
        "title": "한 페이지가 될 수 있게",
        "artist": "DAY6(데이식스)",
        "timestamp": "2025-08-27 16:00"
      },
      {
        "rank": 56,
        "title": "Welcome to the Show",
        "artist": "DAY6(데이식스)",
        "timestamp": "2025-08-27 16:00"
      },
      {
        "rank": 67,
        "title": "예뻤어",
        "artist": "DAY6(데이식스)",
        "timestamp": "2025-08-27 16:00"
      }
    ],
    "flo": [
      {
        "rank": 41,
        "title": "HAPPY",
        "artist": "DAY6 (데이식스)",
        "timestamp": "2025-08-27 16:00"
      },
      {
        "rank": 42,
        "title": "한 페이지가 될 수 있게",
        "artist": "DAY6 (데이식스)",
        "timestamp": "2025-08-27 16:00"
      },
      {
        "rank": 64,
        "title": "Welcome to the Show",
        "artist": "DAY6 (데이식스)",
        "timestamp": "2025-08-27 16:00"
      }
    ]
  },
  "2025-08-27 17:00:00": {
    "_processed_at": "2025-08-27T17:26:44.584958",
    "melon_top100": [
      {
        "rank": 28,
        "title": "HAPPY",
        "artist": "DAY6 (데이식스)",
        "timestamp": "2025-08-27 17:00",
        "chart_type": "TOP100"
      },
      {
        "rank": 31,
        "title": "한 페이지가 될 수 있게",
        "artist": "DAY6 (데이식스)",
        "timestamp": "2025-08-27 17:00",
        "chart_type": "TOP100"
      },
      {
        "rank": 41,
        "title": "Welcome to the Show",
        "artist": "DAY6 (데이식스)",
        "timestamp": "2025-08-27 17:00",
        "chart_type": "TOP100"
      },
      {
        "rank": 47,
        "title": "예뻤어",
        "artist": "DAY6 (데이식스)",
        "timestamp": "2025-08-27 17:00",
        "chart_type": "TOP100"
      }
    ],
    "melon_hot100": [
      {
        "rank": null,
        "timestamp": "2025-08-27 17:00:00",
        "chart_type": "HOT100"
      }
    ],
    "melon": [
      {
        "rank": 28,
        "title": "HAPPY",
        "artist": "DAY6 (데이식스)",
        "timestamp": "2025-08-27 17:00",
        "chart_type": "TOP100"
      },
      {
        "rank": 31,
        "title": "한 페이지가 될 수 있게",
        "artist": "DAY6 (데이식스)",
        "timestamp": "2025-08-27 17:00",
        "chart_type": "TOP100"
      },
      {
        "rank": 41,
        "title": "Welcome to the Show",
        "artist": "DAY6 (데이식스)",
        "timestamp": "2025-08-27 17:00",
        "chart_type": "TOP100"
      },
      {
        "rank": 47,
        "title": "예뻤어",
        "artist": "DAY6 (데이식스)",
        "timestamp": "2025-08-27 17:00",
        "chart_type": "TOP100"
      }
    ],
    "genie": [
      {
        "rank": 20,
        "title": "HAPPY",
        "artist": "DAY6 (데이식스)",
        "timestamp": "2025-08-27 17:00"
      },
      {
        "rank": 24,
        "title": "한 페이지가 될 수 있게",
        "artist": "DAY6 (데이식스)",
        "timestamp": "2025-08-27 17:00"
      },
      {
        "rank": 36,
        "title": "Welcome to the Show",
        "artist": "DAY6 (데이식스)",
        "timestamp": "2025-08-27 17:00"
      },
      {
        "rank": 40,
        "title": "예뻤어",
        "artist": "DAY6 (데이식스)",
        "timestamp": "2025-08-27 17:00"
      },
      {
        "rank": null,
        "title": "Congratulations",
        "artist": "DAY6 (데이식스)",
        "timestamp": "2025-08-27 17:00"
      }
    ],
    "bugs": [
      {
        "rank": null,
        "timestamp": "2025-08-27 17:00:00"
      }
    ],
    "vibe": [
      {
        "rank": 30,
        "title": "HAPPY",
        "artist": "DAY6(데이식스)",
        "timestamp": "2025-08-27 17:00"
      },
      {
        "rank": 32,
        "title": "한 페이지가 될 수 있게",
        "artist": "DAY6(데이식스)",
        "timestamp": "2025-08-27 17:00"
      },
      {
        "rank": 56,
        "title": "Welcome to the Show",
        "artist": "DAY6(데이식스)",
        "timestamp": "2025-08-27 17:00"
      },
      {
        "rank": 67,
        "title": "예뻤어",
        "artist": "DAY6(데이식스)",
        "timestamp": "2025-08-27 17:00"
      }
    ],
    "flo": [
      {
        "rank": 41,
        "title": "HAPPY",
        "artist": "DAY6 (데이식스)",
        "timestamp": "2025-08-27 17:00"
      },
      {
        "rank": 42,
        "title": "한 페이지가 될 수 있게",
        "artist": "DAY6 (데이식스)",
        "timestamp": "2025-08-27 17:00"
      },
      {
        "rank": 64,
        "title": "Welcome to the Show",
        "artist": "DAY6 (데이식스)",
        "timestamp": "2025-08-27 17:00"
      }
    ]
  },
  "2025-08-27 18:00:00": {
    "_processed_at": "2025-08-27T18:20:54.678304",
    "melon_top100": [
      {
        "rank": 28,
        "title": "HAPPY",
        "artist": "DAY6 (데이식스)",
        "timestamp": "2025-08-27 18:00",
        "chart_type": "TOP100"
      },
      {
        "rank": 31,
        "title": "한 페이지가 될 수 있게",
        "artist": "DAY6 (데이식스)",
        "timestamp": "2025-08-27 18:00",
        "chart_type": "TOP100"
      },
      {
        "rank": 43,
        "title": "Welcome to the Show",
        "artist": "DAY6 (데이식스)",
        "timestamp": "2025-08-27 18:00",
        "chart_type": "TOP100"
      },
      {
        "rank": 46,
        "title": "예뻤어",
        "artist": "DAY6 (데이식스)",
        "timestamp": "2025-08-27 18:00",
        "chart_type": "TOP100"
      }
    ],
    "melon_hot100": [
      {
        "rank": null,
        "timestamp": "2025-08-27 18:00:00",
        "chart_type": "HOT100"
      }
    ],
    "melon": [
      {
        "rank": 28,
        "title": "HAPPY",
        "artist": "DAY6 (데이식스)",
        "timestamp": "2025-08-27 18:00",
        "chart_type": "TOP100"
      },
      {
        "rank": 31,
        "title": "한 페이지가 될 수 있게",
        "artist": "DAY6 (데이식스)",
        "timestamp": "2025-08-27 18:00",
        "chart_type": "TOP100"
      },
      {
        "rank": 43,
        "title": "Welcome to the Show",
        "artist": "DAY6 (데이식스)",
        "timestamp": "2025-08-27 18:00",
        "chart_type": "TOP100"
      },
      {
        "rank": 46,
        "title": "예뻤어",
        "artist": "DAY6 (데이식스)",
        "timestamp": "2025-08-27 18:00",
        "chart_type": "TOP100"
      }
    ],
    "genie": [
      {
        "rank": 19,
        "title": "HAPPY",
        "artist": "DAY6 (데이식스)",
        "timestamp": "2025-08-27 18:00"
      },
      {
        "rank": 26,
        "title": "한 페이지가 될 수 있게",
        "artist": "DAY6 (데이식스)",
        "timestamp": "2025-08-27 18:00"
      },
      {
        "rank": 31,
        "title": "Welcome to the Show",
        "artist": "DAY6 (데이식스)",
        "timestamp": "2025-08-27 18:00"
      },
      {
        "rank": 41,
        "title": "예뻤어",
        "artist": "DAY6 (데이식스)",
        "timestamp": "2025-08-27 18:00"
      },
      {
        "rank": null,
        "title": "Congratulations",
        "artist": "DAY6 (데이식스)",
        "timestamp": "2025-08-27 18:00"
      }
    ],
    "bugs": [
      {
        "rank": null,
        "timestamp": "2025-08-27 18:00:00"
      }
    ],
    "vibe": [
      {
        "rank": 30,
        "title": "HAPPY",
        "artist": "DAY6(데이식스)",
        "timestamp": "2025-08-27 18:00"
      },
      {
        "rank": 32,
        "title": "한 페이지가 될 수 있게",
        "artist": "DAY6(데이식스)",
        "timestamp": "2025-08-27 18:00"
      },
      {
        "rank": 56,
        "title": "Welcome to the Show",
        "artist": "DAY6(데이식스)",
        "timestamp": "2025-08-27 18:00"
      },
      {
        "rank": 67,
        "title": "예뻤어",
        "artist": "DAY6(데이식스)",
        "timestamp": "2025-08-27 18:00"
      }
    ],
    "flo": [
      {
        "rank": 41,
        "title": "HAPPY",
        "artist": "DAY6 (데이식스)",
        "timestamp": "2025-08-27 18:00"
      },
      {
        "rank": 42,
        "title": "한 페이지가 될 수 있게",
        "artist": "DAY6 (데이식스)",
        "timestamp": "2025-08-27 18:00"
      },
      {
        "rank": 64,
        "title": "Welcome to the Show",
        "artist": "DAY6 (데이식스)",
        "timestamp": "2025-08-27 18:00"
      }
    ]
  },
  "2025-08-27 19:00:00": {
    "_processed_at": "2025-08-27T19:46:23.292547",
    "melon_top100": [
      {
        "rank": 25,
        "title": "HAPPY",
        "artist": "DAY6 (데이식스)",
        "timestamp": "2025-08-27 19:00",
        "chart_type": "TOP100"
      },
      {
        "rank": 31,
        "title": "한 페이지가 될 수 있게",
        "artist": "DAY6 (데이식스)",
        "timestamp": "2025-08-27 19:00",
        "chart_type": "TOP100"
      },
      {
        "rank": 42,
        "title": "Welcome to the Show",
        "artist": "DAY6 (데이식스)",
        "timestamp": "2025-08-27 19:00",
        "chart_type": "TOP100"
      },
      {
        "rank": 47,
        "title": "예뻤어",
        "artist": "DAY6 (데이식스)",
        "timestamp": "2025-08-27 19:00",
        "chart_type": "TOP100"
      }
    ],
    "melon_hot100": [
      {
        "rank": null,
        "timestamp": "2025-08-27 19:00:00",
        "chart_type": "HOT100"
      }
    ],
    "melon": [
      {
        "rank": 25,
        "title": "HAPPY",
        "artist": "DAY6 (데이식스)",
        "timestamp": "2025-08-27 19:00",
        "chart_type": "TOP100"
      },
      {
        "rank": 31,
        "title": "한 페이지가 될 수 있게",
        "artist": "DAY6 (데이식스)",
        "timestamp": "2025-08-27 19:00",
        "chart_type": "TOP100"
      },
      {
        "rank": 42,
        "title": "Welcome to the Show",
        "artist": "DAY6 (데이식스)",
        "timestamp": "2025-08-27 19:00",
        "chart_type": "TOP100"
      },
      {
        "rank": 47,
        "title": "예뻤어",
        "artist": "DAY6 (데이식스)",
        "timestamp": "2025-08-27 19:00",
        "chart_type": "TOP100"
      }
    ],
    "genie": [
      {
        "rank": 20,
        "title": "HAPPY",
        "artist": "DAY6 (데이식스)",
        "timestamp": "2025-08-27 19:00"
      },
      {
        "rank": 27,
        "title": "한 페이지가 될 수 있게",
        "artist": "DAY6 (데이식스)",
        "timestamp": "2025-08-27 19:00"
      },
      {
        "rank": 35,
        "title": "Welcome to the Show",
        "artist": "DAY6 (데이식스)",
        "timestamp": "2025-08-27 19:00"
      },
      {
        "rank": 39,
        "title": "예뻤어",
        "artist": "DAY6 (데이식스)",
        "timestamp": "2025-08-27 19:00"
      },
      {
        "rank": null,
        "title": "Congratulations",
        "artist": "DAY6 (데이식스)",
        "timestamp": "2025-08-27 19:00"
      }
    ],
    "bugs": [
      {
        "rank": null,
        "timestamp": "2025-08-27 19:00:00"
      }
    ],
    "vibe": [
      {
        "rank": 30,
        "title": "HAPPY",
        "artist": "DAY6(데이식스)",
        "timestamp": "2025-08-27 19:00"
      },
      {
        "rank": 32,
        "title": "한 페이지가 될 수 있게",
        "artist": "DAY6(데이식스)",
        "timestamp": "2025-08-27 19:00"
      },
      {
        "rank": 56,
        "title": "Welcome to the Show",
        "artist": "DAY6(데이식스)",
        "timestamp": "2025-08-27 19:00"
      },
      {
        "rank": 67,
        "title": "예뻤어",
        "artist": "DAY6(데이식스)",
        "timestamp": "2025-08-27 19:00"
      }
    ],
    "flo": [
      {
        "rank": 38,
        "title": "HAPPY",
        "artist": "DAY6 (데이식스)",
        "timestamp": "2025-08-27 19:00"
      },
      {
        "rank": 41,
        "title": "한 페이지가 될 수 있게",
        "artist": "DAY6 (데이식스)",
        "timestamp": "2025-08-27 19:00"
      },
      {
        "rank": 64,
        "title": "Welcome to the Show",
        "artist": "DAY6 (데이식스)",
        "timestamp": "2025-08-27 19:00"
      },
      {
        "rank": 95,
        "title": "예뻤어",
        "artist": "DAY6 (데이식스)",
        "timestamp": "2025-08-27 19:00"
      }
    ]
  },
  "2025-08-27 20:00:00": {
    "_processed_at": "2025-08-27T20:41:45.805078",
    "melon_top100": [
      {
        "rank": 27,
        "title": "HAPPY",
        "artist": "DAY6 (데이식스)",
        "timestamp": "2025-08-27 20:00",
        "chart_type": "TOP100"
      },
      {
        "rank": 31,
        "title": "한 페이지가 될 수 있게",
        "artist": "DAY6 (데이식스)",
        "timestamp": "2025-08-27 20:00",
        "chart_type": "TOP100"
      },
      {
        "rank": 40,
        "title": "Welcome to the Show",
        "artist": "DAY6 (데이식스)",
        "timestamp": "2025-08-27 20:00",
        "chart_type": "TOP100"
      },
      {
        "rank": 46,
        "title": "예뻤어",
        "artist": "DAY6 (데이식스)",
        "timestamp": "2025-08-27 20:00",
        "chart_type": "TOP100"
      }
    ],
    "melon_hot100": [
      {
        "rank": null,
        "timestamp": "2025-08-27 20:00:00",
        "chart_type": "HOT100"
      }
    ],
    "melon": [
      {
        "rank": 27,
        "title": "HAPPY",
        "artist": "DAY6 (데이식스)",
        "timestamp": "2025-08-27 20:00",
        "chart_type": "TOP100"
      },
      {
        "rank": 31,
        "title": "한 페이지가 될 수 있게",
        "artist": "DAY6 (데이식스)",
        "timestamp": "2025-08-27 20:00",
        "chart_type": "TOP100"
      },
      {
        "rank": 40,
        "title": "Welcome to the Show",
        "artist": "DAY6 (데이식스)",
        "timestamp": "2025-08-27 20:00",
        "chart_type": "TOP100"
      },
      {
        "rank": 46,
        "title": "예뻤어",
        "artist": "DAY6 (데이식스)",
        "timestamp": "2025-08-27 20:00",
        "chart_type": "TOP100"
      }
    ],
    "genie": [
      {
        "rank": 22,
        "title": "HAPPY",
        "artist": "DAY6 (데이식스)",
        "timestamp": "2025-08-27 20:00"
      },
      {
        "rank": 27,
        "title": "한 페이지가 될 수 있게",
        "artist": "DAY6 (데이식스)",
        "timestamp": "2025-08-27 20:00"
      },
      {
        "rank": 38,
        "title": "Welcome to the Show",
        "artist": "DAY6 (데이식스)",
        "timestamp": "2025-08-27 20:00"
      },
      {
        "rank": 43,
        "title": "예뻤어",
        "artist": "DAY6 (데이식스)",
        "timestamp": "2025-08-27 20:00"
      },
      {
        "rank": null,
        "title": "Congratulations",
        "artist": "DAY6 (데이식스)",
        "timestamp": "2025-08-27 20:00"
      }
    ],
    "bugs": [
      {
        "rank": null,
        "timestamp": "2025-08-27 20:00:00"
      }
    ],
    "vibe": [
      {
        "rank": 30,
        "title": "HAPPY",
        "artist": "DAY6(데이식스)",
        "timestamp": "2025-08-27 20:00"
      },
      {
        "rank": 32,
        "title": "한 페이지가 될 수 있게",
        "artist": "DAY6(데이식스)",
        "timestamp": "2025-08-27 20:00"
      },
      {
        "rank": 56,
        "title": "Welcome to the Show",
        "artist": "DAY6(데이식스)",
        "timestamp": "2025-08-27 20:00"
      },
      {
        "rank": 67,
        "title": "예뻤어",
        "artist": "DAY6(데이식스)",
        "timestamp": "2025-08-27 20:00"
      }
    ],
    "flo": [
      {
        "rank": 38,
        "title": "HAPPY",
        "artist": "DAY6 (데이식스)",
        "timestamp": "2025-08-27 20:00"
      },
      {
        "rank": 41,
        "title": "한 페이지가 될 수 있게",
        "artist": "DAY6 (데이식스)",
        "timestamp": "2025-08-27 20:00"
      },
      {
        "rank": 64,
        "title": "Welcome to the Show",
        "artist": "DAY6 (데이식스)",
        "timestamp": "2025-08-27 20:00"
      },
      {
        "rank": 94,
        "title": "예뻤어",
        "artist": "DAY6 (데이식스)",
        "timestamp": "2025-08-27 20:00"
      }
    ]
  },
  "2025-08-27 21:00:00": {
    "_processed_at": "2025-08-27T21:40:51.777338",
    "melon_top100": [
      {
        "rank": 27,
        "title": "HAPPY",
        "artist": "DAY6 (데이식스)",
        "timestamp": "2025-08-27 21:00",
        "chart_type": "TOP100"
      },
      {
        "rank": 32,
        "title": "한 페이지가 될 수 있게",
        "artist": "DAY6 (데이식스)",
        "timestamp": "2025-08-27 21:00",
        "chart_type": "TOP100"
      },
      {
        "rank": 42,
        "title": "Welcome to the Show",
        "artist": "DAY6 (데이식스)",
        "timestamp": "2025-08-27 21:00",
        "chart_type": "TOP100"
      },
      {
        "rank": 47,
        "title": "예뻤어",
        "artist": "DAY6 (데이식스)",
        "timestamp": "2025-08-27 21:00",
        "chart_type": "TOP100"
      }
    ],
    "melon_hot100": [
      {
        "rank": null,
        "timestamp": "2025-08-27 21:00:00",
        "chart_type": "HOT100"
      }
    ],
    "melon": [
      {
        "rank": 27,
        "title": "HAPPY",
        "artist": "DAY6 (데이식스)",
        "timestamp": "2025-08-27 21:00",
        "chart_type": "TOP100"
      },
      {
        "rank": 32,
        "title": "한 페이지가 될 수 있게",
        "artist": "DAY6 (데이식스)",
        "timestamp": "2025-08-27 21:00",
        "chart_type": "TOP100"
      },
      {
        "rank": 42,
        "title": "Welcome to the Show",
        "artist": "DAY6 (데이식스)",
        "timestamp": "2025-08-27 21:00",
        "chart_type": "TOP100"
      },
      {
        "rank": 47,
        "title": "예뻤어",
        "artist": "DAY6 (데이식스)",
        "timestamp": "2025-08-27 21:00",
        "chart_type": "TOP100"
      }
    ],
    "genie": [
      {
        "rank": 22,
        "title": "HAPPY",
        "artist": "DAY6 (데이식스)",
        "timestamp": "2025-08-27 21:00"
      },
      {
        "rank": 31,
        "title": "한 페이지가 될 수 있게",
        "artist": "DAY6 (데이식스)",
        "timestamp": "2025-08-27 21:00"
      },
      {
        "rank": 42,
        "title": "Welcome to the Show",
        "artist": "DAY6 (데이식스)",
        "timestamp": "2025-08-27 21:00"
      },
      {
        "rank": 49,
        "title": "예뻤어",
        "artist": "DAY6 (데이식스)",
        "timestamp": "2025-08-27 21:00"
      },
      {
        "rank": null,
        "title": "Congratulations",
        "artist": "DAY6 (데이식스)",
        "timestamp": "2025-08-27 21:00"
      }
    ],
    "bugs": [
      {
        "rank": null,
        "timestamp": "2025-08-27 21:00:00"
      }
    ],
    "vibe": [
      {
        "rank": 30,
        "title": "HAPPY",
        "artist": "DAY6(데이식스)",
        "timestamp": "2025-08-27 21:00"
      },
      {
        "rank": 32,
        "title": "한 페이지가 될 수 있게",
        "artist": "DAY6(데이식스)",
        "timestamp": "2025-08-27 21:00"
      },
      {
        "rank": 56,
        "title": "Welcome to the Show",
        "artist": "DAY6(데이식스)",
        "timestamp": "2025-08-27 21:00"
      },
      {
        "rank": 67,
        "title": "예뻤어",
        "artist": "DAY6(데이식스)",
        "timestamp": "2025-08-27 21:00"
      }
    ],
    "flo": [
      {
        "rank": 38,
        "title": "HAPPY",
        "artist": "DAY6 (데이식스)",
        "timestamp": "2025-08-27 21:00"
      },
      {
        "rank": 41,
        "title": "한 페이지가 될 수 있게",
        "artist": "DAY6 (데이식스)",
        "timestamp": "2025-08-27 21:00"
      },
      {
        "rank": 64,
        "title": "Welcome to the Show",
        "artist": "DAY6 (데이식스)",
        "timestamp": "2025-08-27 21:00"
      },
      {
        "rank": 95,
        "title": "예뻤어",
        "artist": "DAY6 (데이식스)",
        "timestamp": "2025-08-27 21:00"
      }
    ]
  },
  "2025-08-27 22:00:00": {
    "_processed_at": "2025-08-27T22:28:55.974453",
    "melon_top100": [
      {
        "rank": 28,
        "title": "HAPPY",
        "artist": "DAY6 (데이식스)",
        "timestamp": "2025-08-27 22:00",
        "chart_type": "TOP100"
      },
      {
        "rank": 32,
        "title": "한 페이지가 될 수 있게",
        "artist": "DAY6 (데이식스)",
        "timestamp": "2025-08-27 22:00",
        "chart_type": "TOP100"
      },
      {
        "rank": 43,
        "title": "Welcome to the Show",
        "artist": "DAY6 (데이식스)",
        "timestamp": "2025-08-27 22:00",
        "chart_type": "TOP100"
      },
      {
        "rank": 49,
        "title": "예뻤어",
        "artist": "DAY6 (데이식스)",
        "timestamp": "2025-08-27 22:00",
        "chart_type": "TOP100"
      }
    ],
    "melon_hot100": [
      {
        "rank": null,
        "timestamp": "2025-08-27 22:00:00",
        "chart_type": "HOT100"
      }
    ],
    "melon": [
      {
        "rank": 28,
        "title": "HAPPY",
        "artist": "DAY6 (데이식스)",
        "timestamp": "2025-08-27 22:00",
        "chart_type": "TOP100"
      },
      {
        "rank": 32,
        "title": "한 페이지가 될 수 있게",
        "artist": "DAY6 (데이식스)",
        "timestamp": "2025-08-27 22:00",
        "chart_type": "TOP100"
      },
      {
        "rank": 43,
        "title": "Welcome to the Show",
        "artist": "DAY6 (데이식스)",
        "timestamp": "2025-08-27 22:00",
        "chart_type": "TOP100"
      },
      {
        "rank": 49,
        "title": "예뻤어",
        "artist": "DAY6 (데이식스)",
        "timestamp": "2025-08-27 22:00",
        "chart_type": "TOP100"
      }
    ],
    "genie": [
      {
        "rank": 26,
        "title": "HAPPY",
        "artist": "DAY6 (데이식스)",
        "timestamp": "2025-08-27 22:00"
      },
      {
        "rank": 39,
        "title": "한 페이지가 될 수 있게",
        "artist": "DAY6 (데이식스)",
        "timestamp": "2025-08-27 22:00"
      },
      {
        "rank": 48,
        "title": "Welcome to the Show",
        "artist": "DAY6 (데이식스)",
        "timestamp": "2025-08-27 22:00"
      },
      {
        "rank": 50,
        "title": "예뻤어",
        "artist": "DAY6 (데이식스)",
        "timestamp": "2025-08-27 22:00"
      },
      {
        "rank": null,
        "title": "Congratulations",
        "artist": "DAY6 (데이식스)",
        "timestamp": "2025-08-27 22:00"
      }
    ],
    "bugs": [
      {
        "rank": null,
        "timestamp": "2025-08-27 22:00:00"
      }
    ],
    "vibe": [
      {
        "rank": 30,
        "title": "HAPPY",
        "artist": "DAY6(데이식스)",
        "timestamp": "2025-08-27 22:00"
      },
      {
        "rank": 32,
        "title": "한 페이지가 될 수 있게",
        "artist": "DAY6(데이식스)",
        "timestamp": "2025-08-27 22:00"
      },
      {
        "rank": 56,
        "title": "Welcome to the Show",
        "artist": "DAY6(데이식스)",
        "timestamp": "2025-08-27 22:00"
      },
      {
        "rank": 67,
        "title": "예뻤어",
        "artist": "DAY6(데이식스)",
        "timestamp": "2025-08-27 22:00"
      }
    ],
    "flo": [
      {
        "rank": 39,
        "title": "HAPPY",
        "artist": "DAY6 (데이식스)",
        "timestamp": "2025-08-27 22:00"
      },
      {
        "rank": 42,
        "title": "한 페이지가 될 수 있게",
        "artist": "DAY6 (데이식스)",
        "timestamp": "2025-08-27 22:00"
      },
      {
        "rank": 63,
        "title": "Welcome to the Show",
        "artist": "DAY6 (데이식스)",
        "timestamp": "2025-08-27 22:00"
      },
      {
        "rank": 94,
        "title": "예뻤어",
        "artist": "DAY6 (데이식스)",
        "timestamp": "2025-08-27 22:00"
      }
    ]
  },
  "2025-08-27 23:00:00": {
    "_processed_at": "2025-08-27T23:19:27.995647",
    "melon_top100": [
      {
        "rank": 28,
        "title": "HAPPY",
        "artist": "DAY6 (데이식스)",
        "timestamp": "2025-08-27 23:00",
        "chart_type": "TOP100"
      },
      {
        "rank": 34,
        "title": "한 페이지가 될 수 있게",
        "artist": "DAY6 (데이식스)",
        "timestamp": "2025-08-27 23:00",
        "chart_type": "TOP100"
      },
      {
        "rank": 47,
        "title": "Welcome to the Show",
        "artist": "DAY6 (데이식스)",
        "timestamp": "2025-08-27 23:00",
        "chart_type": "TOP100"
      },
      {
        "rank": 52,
        "title": "예뻤어",
        "artist": "DAY6 (데이식스)",
        "timestamp": "2025-08-27 23:00",
        "chart_type": "TOP100"
      }
    ],
    "melon_hot100": [
      {
        "rank": null,
        "timestamp": "2025-08-27 23:00:00",
        "chart_type": "HOT100"
      }
    ],
    "melon": [
      {
        "rank": 28,
        "title": "HAPPY",
        "artist": "DAY6 (데이식스)",
        "timestamp": "2025-08-27 23:00",
        "chart_type": "TOP100"
      },
      {
        "rank": 34,
        "title": "한 페이지가 될 수 있게",
        "artist": "DAY6 (데이식스)",
        "timestamp": "2025-08-27 23:00",
        "chart_type": "TOP100"
      },
      {
        "rank": 47,
        "title": "Welcome to the Show",
        "artist": "DAY6 (데이식스)",
        "timestamp": "2025-08-27 23:00",
        "chart_type": "TOP100"
      },
      {
        "rank": 52,
        "title": "예뻤어",
        "artist": "DAY6 (데이식스)",
        "timestamp": "2025-08-27 23:00",
        "chart_type": "TOP100"
      }
    ],
    "genie": [
      {
        "rank": 35,
        "title": "HAPPY",
        "artist": "DAY6 (데이식스)",
        "timestamp": "2025-08-27 23:00"
      },
      {
        "rank": 39,
        "title": "한 페이지가 될 수 있게",
        "artist": "DAY6 (데이식스)",
        "timestamp": "2025-08-27 23:00"
      },
      {
        "rank": 50,
        "title": "Welcome to the Show",
        "artist": "DAY6 (데이식스)",
        "timestamp": "2025-08-27 23:00"
      },
      {
        "rank": 53,
        "title": "예뻤어",
        "artist": "DAY6 (데이식스)",
        "timestamp": "2025-08-27 23:00"
      },
      {
        "rank": 96,
        "title": "Congratulations",
        "artist": "DAY6 (데이식스)",
        "timestamp": "2025-08-27 23:00"
      }
    ],
    "bugs": [
      {
        "rank": null,
        "timestamp": "2025-08-27 23:00:00"
      }
    ],
    "vibe": [
      {
        "rank": 30,
        "title": "HAPPY",
        "artist": "DAY6(데이식스)",
        "timestamp": "2025-08-27 23:00"
      },
      {
        "rank": 32,
        "title": "한 페이지가 될 수 있게",
        "artist": "DAY6(데이식스)",
        "timestamp": "2025-08-27 23:00"
      },
      {
        "rank": 56,
        "title": "Welcome to the Show",
        "artist": "DAY6(데이식스)",
        "timestamp": "2025-08-27 23:00"
      },
      {
        "rank": 67,
        "title": "예뻤어",
        "artist": "DAY6(데이식스)",
        "timestamp": "2025-08-27 23:00"
      }
    ],
    "flo": [
      {
        "rank": 39,
        "title": "HAPPY",
        "artist": "DAY6 (데이식스)",
        "timestamp": "2025-08-27 23:00"
      },
      {
        "rank": 42,
        "title": "한 페이지가 될 수 있게",
        "artist": "DAY6 (데이식스)",
        "timestamp": "2025-08-27 23:00"
      },
      {
        "rank": 64,
        "title": "Welcome to the Show",
        "artist": "DAY6 (데이식스)",
        "timestamp": "2025-08-27 23:00"
      },
      {
        "rank": 98,
        "title": "예뻤어",
        "artist": "DAY6 (데이식스)",
        "timestamp": "2025-08-27 23:00"
      }
    ]
  },
  "2025-08-28 00:00:00": {
    "_processed_at": "2025-08-28T00:20:57.733803",
    "melon_top100": [
      {
        "rank": 34,
        "title": "HAPPY",
        "artist": "DAY6 (데이식스)",
        "timestamp": "2025-08-28 00:00",
        "chart_type": "TOP100"
      },
      {
        "rank": 39,
        "title": "한 페이지가 될 수 있게",
        "artist": "DAY6 (데이식스)",
        "timestamp": "2025-08-28 00:00",
        "chart_type": "TOP100"
      },
      {
        "rank": 50,
        "title": "Welcome to the Show",
        "artist": "DAY6 (데이식스)",
        "timestamp": "2025-08-28 00:00",
        "chart_type": "TOP100"
      },
      {
        "rank": 55,
        "title": "예뻤어",
        "artist": "DAY6 (데이식스)",
        "timestamp": "2025-08-28 00:00",
        "chart_type": "TOP100"
      }
    ],
    "melon_hot100": [
      {
        "rank": null,
        "timestamp": "2025-08-28 00:00:00",
        "chart_type": "HOT100"
      }
    ],
    "melon": [
      {
        "rank": 34,
        "title": "HAPPY",
        "artist": "DAY6 (데이식스)",
        "timestamp": "2025-08-28 00:00",
        "chart_type": "TOP100"
      },
      {
        "rank": 39,
        "title": "한 페이지가 될 수 있게",
        "artist": "DAY6 (데이식스)",
        "timestamp": "2025-08-28 00:00",
        "chart_type": "TOP100"
      },
      {
        "rank": 50,
        "title": "Welcome to the Show",
        "artist": "DAY6 (데이식스)",
        "timestamp": "2025-08-28 00:00",
        "chart_type": "TOP100"
      },
      {
        "rank": 55,
        "title": "예뻤어",
        "artist": "DAY6 (데이식스)",
        "timestamp": "2025-08-28 00:00",
        "chart_type": "TOP100"
      }
    ],
    "genie": [
      {
        "rank": 35,
        "title": "HAPPY",
        "artist": "DAY6 (데이식스)",
        "timestamp": "2025-08-28 00:00"
      },
      {
        "rank": 39,
        "title": "한 페이지가 될 수 있게",
        "artist": "DAY6 (데이식스)",
        "timestamp": "2025-08-28 00:00"
      },
      {
        "rank": 50,
        "title": "Welcome to the Show",
        "artist": "DAY6 (데이식스)",
        "timestamp": "2025-08-28 00:00"
      },
      {
        "rank": 51,
        "title": "예뻤어",
        "artist": "DAY6 (데이식스)",
        "timestamp": "2025-08-28 00:00"
      },
      {
        "rank": null,
        "title": "Congratulations",
        "artist": "DAY6 (데이식스)",
        "timestamp": "2025-08-28 00:00"
      }
    ],
    "bugs": [
      {
        "rank": null,
        "timestamp": "2025-08-28 00:00:00"
      }
    ],
    "vibe": [
      {
        "rank": 30,
        "title": "HAPPY",
        "artist": "DAY6(데이식스)",
        "timestamp": "2025-08-28 00:00"
      },
      {
        "rank": 32,
        "title": "한 페이지가 될 수 있게",
        "artist": "DAY6(데이식스)",
        "timestamp": "2025-08-28 00:00"
      },
      {
        "rank": 56,
        "title": "Welcome to the Show",
        "artist": "DAY6(데이식스)",
        "timestamp": "2025-08-28 00:00"
      },
      {
        "rank": 67,
        "title": "예뻤어",
        "artist": "DAY6(데이식스)",
        "timestamp": "2025-08-28 00:00"
      }
    ],
    "flo": [
      {
        "rank": 40,
        "title": "HAPPY",
        "artist": "DAY6 (데이식스)",
        "timestamp": "2025-08-28 00:00"
      },
      {
        "rank": 42,
        "title": "한 페이지가 될 수 있게",
        "artist": "DAY6 (데이식스)",
        "timestamp": "2025-08-28 00:00"
      },
      {
        "rank": 64,
        "title": "Welcome to the Show",
        "artist": "DAY6 (데이식스)",
        "timestamp": "2025-08-28 00:00"
      },
      {
        "rank": null,
        "title": "예뻤어",
        "artist": "DAY6 (데이식스)",
        "timestamp": "2025-08-28 00:00"
      }
    ]
  },
  "2025-08-28 01:00:00": {
    "_processed_at": "2025-08-28T01:43:18.632383",
    "melon_top100": [
      {
        "rank": 24,
        "title": "HAPPY",
        "artist": "DAY6 (데이식스)",
        "timestamp": "2025-08-28 01:00:00",
        "chart_type": "TOP100"
      },
      {
        "rank": 30,
        "title": "한 페이지가 될 수 있게",
        "artist": "DAY6 (데이식스)",
        "timestamp": "2025-08-28 01:00:00",
        "chart_type": "TOP100"
      },
      {
        "rank": 40,
        "title": "Welcome to the Show",
        "artist": "DAY6 (데이식스)",
        "timestamp": "2025-08-28 01:00:00",
        "chart_type": "TOP100"
      },
      {
        "rank": 45,
        "title": "예뻤어",
        "artist": "DAY6 (데이식스)",
        "timestamp": "2025-08-28 01:00:00",
        "chart_type": "TOP100"
      }
    ],
    "melon_hot100": [
      {
        "rank": null,
        "timestamp": "2025-08-28 01:00:00",
        "chart_type": "HOT100"
      }
    ],
    "melon": [
      {
        "rank": 24,
        "title": "HAPPY",
        "artist": "DAY6 (데이식스)",
        "timestamp": "2025-08-28 01:00:00",
        "chart_type": "TOP100"
      },
      {
        "rank": 30,
        "title": "한 페이지가 될 수 있게",
        "artist": "DAY6 (데이식스)",
        "timestamp": "2025-08-28 01:00:00",
        "chart_type": "TOP100"
      },
      {
        "rank": 40,
        "title": "Welcome to the Show",
        "artist": "DAY6 (데이식스)",
        "timestamp": "2025-08-28 01:00:00",
        "chart_type": "TOP100"
      },
      {
        "rank": 45,
        "title": "예뻤어",
        "artist": "DAY6 (데이식스)",
        "timestamp": "2025-08-28 01:00:00",
        "chart_type": "TOP100"
      }
    ],
    "genie": [
      {
        "rank": 45,
        "title": "HAPPY",
        "artist": "DAY6 (데이식스)",
        "timestamp": "2025-08-28 01:00:00"
      },
      {
        "rank": 53,
        "title": "한 페이지가 될 수 있게",
        "artist": "DAY6 (데이식스)",
        "timestamp": "2025-08-28 01:00:00"
      },
      {
        "rank": 63,
        "title": "예뻤어",
        "artist": "DAY6 (데이식스)",
        "timestamp": "2025-08-28 01:00:00"
      },
      {
        "rank": 68,
        "title": "Welcome to the Show",
        "artist": "DAY6 (데이식스)",
        "timestamp": "2025-08-28 01:00:00"
      }
    ],
    "bugs": [
      {
        "rank": 32,
        "title": "HAPPY",
        "artist": "DAY6 (데이식스)",
        "timestamp": "2025-08-28 01:00:00"
      },
      {
        "rank": 39,
        "title": "한 페이지가 될 수 있게",
        "artist": "DAY6 (데이식스)",
        "timestamp": "2025-08-28 01:00:00"
      },
      {
        "rank": 58,
        "title": "Maybe Tomorrow",
        "artist": "DAY6 (데이식스)",
        "timestamp": "2025-08-28 01:00:00"
      },
      {
        "rank": 59,
        "title": "Welcome to the Show",
        "artist": "DAY6 (데이식스)",
        "timestamp": "2025-08-28 01:00:00"
      },
      {
        "rank": 73,
        "title": "Congratulations",
        "artist": "DAY6 (데이식스)",
        "timestamp": "2025-08-28 01:00:00"
      },
      {
        "rank": 80,
        "title": "예뻤어",
        "artist": "DAY6 (데이식스)",
        "timestamp": "2025-08-28 01:00:00"
      },
      {
        "rank": 89,
        "title": "녹아내려요",
        "artist": "DAY6 (데이식스)",
        "timestamp": "2025-08-28 01:00:00"
      },
      {
        "rank": 95,
        "title": "Love me or Leave me",
        "artist": "DAY6 (데이식스)",
        "timestamp": "2025-08-28 01:00:00"
      }
    ],
    "vibe": [
      {
        "rank": 30,
        "title": "HAPPY",
        "artist": "DAY6(데이식스)",
        "timestamp": "2025-08-28 01:00:00"
      },
      {
        "rank": 32,
        "title": "한 페이지가 될 수 있게",
        "artist": "DAY6(데이식스)",
        "timestamp": "2025-08-28 01:00:00"
      },
      {
        "rank": 56,
        "title": "Welcome to the Show",
        "artist": "DAY6(데이식스)",
        "timestamp": "2025-08-28 01:00:00"
      },
      {
        "rank": 67,
        "title": "예뻤어",
        "artist": "DAY6(데이식스)",
        "timestamp": "2025-08-28 01:00:00"
      }
    ],
    "flo": [
      {
        "rank": 40,
        "title": "HAPPY",
        "artist": "DAY6 (데이식스)",
        "timestamp": "2025-08-28 01:00:00"
      },
      {
        "rank": 42,
        "title": "한 페이지가 될 수 있게",
        "artist": "DAY6 (데이식스)",
        "timestamp": "2025-08-28 01:00:00"
      },
      {
        "rank": 64,
        "title": "Welcome to the Show",
        "artist": "DAY6 (데이식스)",
        "timestamp": "2025-08-28 01:00:00"
      }
    ]
  },
  "2025-08-28 02:00:00": {
    "_processed_at": "2025-08-28T02:17:28.113519",
    "melon_top100": [
      {
        "rank": 24,
        "title": "HAPPY",
        "artist": "DAY6 (데이식스)",
        "timestamp": "2025-08-28 02:00:00",
        "chart_type": "TOP100"
      },
      {
        "rank": 30,
        "title": "한 페이지가 될 수 있게",
        "artist": "DAY6 (데이식스)",
        "timestamp": "2025-08-28 02:00:00",
        "chart_type": "TOP100"
      },
      {
        "rank": 40,
        "title": "Welcome to the Show",
        "artist": "DAY6 (데이식스)",
        "timestamp": "2025-08-28 02:00:00",
        "chart_type": "TOP100"
      },
      {
        "rank": 45,
        "title": "예뻤어",
        "artist": "DAY6 (데이식스)",
        "timestamp": "2025-08-28 02:00:00",
        "chart_type": "TOP100"
      }
    ],
    "melon_hot100": [
      {
        "rank": null,
        "timestamp": "2025-08-28 02:00:00",
        "chart_type": "HOT100"
      }
    ],
    "melon": [
      {
        "rank": 24,
        "title": "HAPPY",
        "artist": "DAY6 (데이식스)",
        "timestamp": "2025-08-28 02:00:00",
        "chart_type": "TOP100"
      },
      {
        "rank": 30,
        "title": "한 페이지가 될 수 있게",
        "artist": "DAY6 (데이식스)",
        "timestamp": "2025-08-28 02:00:00",
        "chart_type": "TOP100"
      },
      {
        "rank": 40,
        "title": "Welcome to the Show",
        "artist": "DAY6 (데이식스)",
        "timestamp": "2025-08-28 02:00:00",
        "chart_type": "TOP100"
      },
      {
        "rank": 45,
        "title": "예뻤어",
        "artist": "DAY6 (데이식스)",
        "timestamp": "2025-08-28 02:00:00",
        "chart_type": "TOP100"
      }
    ],
    "genie": [
      {
        "rank": 45,
        "title": "HAPPY",
        "artist": "DAY6 (데이식스)",
        "timestamp": "2025-08-28 02:00:00"
      },
      {
        "rank": 53,
        "title": "한 페이지가 될 수 있게",
        "artist": "DAY6 (데이식스)",
        "timestamp": "2025-08-28 02:00:00"
      },
      {
        "rank": 63,
        "title": "예뻤어",
        "artist": "DAY6 (데이식스)",
        "timestamp": "2025-08-28 02:00:00"
      },
      {
        "rank": 68,
        "title": "Welcome to the Show",
        "artist": "DAY6 (데이식스)",
        "timestamp": "2025-08-28 02:00:00"
      }
    ],
    "bugs": [
      {
        "rank": 32,
        "title": "HAPPY",
        "artist": "DAY6 (데이식스)",
        "timestamp": "2025-08-28 02:00:00"
      },
      {
        "rank": 39,
        "title": "한 페이지가 될 수 있게",
        "artist": "DAY6 (데이식스)",
        "timestamp": "2025-08-28 02:00:00"
      },
      {
        "rank": 58,
        "title": "Maybe Tomorrow",
        "artist": "DAY6 (데이식스)",
        "timestamp": "2025-08-28 02:00:00"
      },
      {
        "rank": 59,
        "title": "Welcome to the Show",
        "artist": "DAY6 (데이식스)",
        "timestamp": "2025-08-28 02:00:00"
      },
      {
        "rank": 73,
        "title": "Congratulations",
        "artist": "DAY6 (데이식스)",
        "timestamp": "2025-08-28 02:00:00"
      },
      {
        "rank": 80,
        "title": "예뻤어",
        "artist": "DAY6 (데이식스)",
        "timestamp": "2025-08-28 02:00:00"
      },
      {
        "rank": 89,
        "title": "녹아내려요",
        "artist": "DAY6 (데이식스)",
        "timestamp": "2025-08-28 02:00:00"
      },
      {
        "rank": 95,
        "title": "Love me or Leave me",
        "artist": "DAY6 (데이식스)",
        "timestamp": "2025-08-28 02:00:00"
      }
    ],
    "vibe": [
      {
        "rank": 30,
        "title": "HAPPY",
        "artist": "DAY6(데이식스)",
        "timestamp": "2025-08-28 02:00:00"
      },
      {
        "rank": 32,
        "title": "한 페이지가 될 수 있게",
        "artist": "DAY6(데이식스)",
        "timestamp": "2025-08-28 02:00:00"
      },
      {
        "rank": 56,
        "title": "Welcome to the Show",
        "artist": "DAY6(데이식스)",
        "timestamp": "2025-08-28 02:00:00"
      },
      {
        "rank": 67,
        "title": "예뻤어",
        "artist": "DAY6(데이식스)",
        "timestamp": "2025-08-28 02:00:00"
      }
    ],
    "flo": [
      {
        "rank": 40,
        "title": "HAPPY",
        "artist": "DAY6 (데이식스)",
        "timestamp": "2025-08-28 02:00:00"
      },
      {
        "rank": 42,
        "title": "한 페이지가 될 수 있게",
        "artist": "DAY6 (데이식스)",
        "timestamp": "2025-08-28 02:00:00"
      },
      {
        "rank": 70,
        "title": "Welcome to the Show",
        "artist": "DAY6 (데이식스)",
        "timestamp": "2025-08-28 02:00:00"
      }
    ]
  },
  "2025-08-28 03:00:00": {
    "_processed_at": "2025-08-28T03:28:20.126856",
    "melon_top100": [
      {
        "rank": 24,
        "title": "HAPPY",
        "artist": "DAY6 (데이식스)",
        "timestamp": "2025-08-28 03:00:00",
        "chart_type": "TOP100"
      },
      {
        "rank": 30,
        "title": "한 페이지가 될 수 있게",
        "artist": "DAY6 (데이식스)",
        "timestamp": "2025-08-28 03:00:00",
        "chart_type": "TOP100"
      },
      {
        "rank": 40,
        "title": "Welcome to the Show",
        "artist": "DAY6 (데이식스)",
        "timestamp": "2025-08-28 03:00:00",
        "chart_type": "TOP100"
      },
      {
        "rank": 45,
        "title": "예뻤어",
        "artist": "DAY6 (데이식스)",
        "timestamp": "2025-08-28 03:00:00",
        "chart_type": "TOP100"
      }
    ],
    "melon_hot100": [
      {
        "rank": null,
        "timestamp": "2025-08-28 03:00:00",
        "chart_type": "HOT100"
      }
    ],
    "melon": [
      {
        "rank": 24,
        "title": "HAPPY",
        "artist": "DAY6 (데이식스)",
        "timestamp": "2025-08-28 03:00:00",
        "chart_type": "TOP100"
      },
      {
        "rank": 30,
        "title": "한 페이지가 될 수 있게",
        "artist": "DAY6 (데이식스)",
        "timestamp": "2025-08-28 03:00:00",
        "chart_type": "TOP100"
      },
      {
        "rank": 40,
        "title": "Welcome to the Show",
        "artist": "DAY6 (데이식스)",
        "timestamp": "2025-08-28 03:00:00",
        "chart_type": "TOP100"
      },
      {
        "rank": 45,
        "title": "예뻤어",
        "artist": "DAY6 (데이식스)",
        "timestamp": "2025-08-28 03:00:00",
        "chart_type": "TOP100"
      }
    ],
    "genie": [
      {
        "rank": 45,
        "title": "HAPPY",
        "artist": "DAY6 (데이식스)",
        "timestamp": "2025-08-28 03:00:00"
      },
      {
        "rank": 53,
        "title": "한 페이지가 될 수 있게",
        "artist": "DAY6 (데이식스)",
        "timestamp": "2025-08-28 03:00:00"
      },
      {
        "rank": 63,
        "title": "예뻤어",
        "artist": "DAY6 (데이식스)",
        "timestamp": "2025-08-28 03:00:00"
      },
      {
        "rank": 68,
        "title": "Welcome to the Show",
        "artist": "DAY6 (데이식스)",
        "timestamp": "2025-08-28 03:00:00"
      }
    ],
    "bugs": [
      {
        "rank": 32,
        "title": "HAPPY",
        "artist": "DAY6 (데이식스)",
        "timestamp": "2025-08-28 03:00:00"
      },
      {
        "rank": 39,
        "title": "한 페이지가 될 수 있게",
        "artist": "DAY6 (데이식스)",
        "timestamp": "2025-08-28 03:00:00"
      },
      {
        "rank": 58,
        "title": "Maybe Tomorrow",
        "artist": "DAY6 (데이식스)",
        "timestamp": "2025-08-28 03:00:00"
      },
      {
        "rank": 59,
        "title": "Welcome to the Show",
        "artist": "DAY6 (데이식스)",
        "timestamp": "2025-08-28 03:00:00"
      },
      {
        "rank": 73,
        "title": "Congratulations",
        "artist": "DAY6 (데이식스)",
        "timestamp": "2025-08-28 03:00:00"
      },
      {
        "rank": 80,
        "title": "예뻤어",
        "artist": "DAY6 (데이식스)",
        "timestamp": "2025-08-28 03:00:00"
      },
      {
        "rank": 89,
        "title": "녹아내려요",
        "artist": "DAY6 (데이식스)",
        "timestamp": "2025-08-28 03:00:00"
      },
      {
        "rank": 95,
        "title": "Love me or Leave me",
        "artist": "DAY6 (데이식스)",
        "timestamp": "2025-08-28 03:00:00"
      }
    ],
    "vibe": [
      {
        "rank": 30,
        "title": "HAPPY",
        "artist": "DAY6(데이식스)",
        "timestamp": "2025-08-28 03:00:00"
      },
      {
        "rank": 32,
        "title": "한 페이지가 될 수 있게",
        "artist": "DAY6(데이식스)",
        "timestamp": "2025-08-28 03:00:00"
      },
      {
        "rank": 56,
        "title": "Welcome to the Show",
        "artist": "DAY6(데이식스)",
        "timestamp": "2025-08-28 03:00:00"
      },
      {
        "rank": 67,
        "title": "예뻤어",
        "artist": "DAY6(데이식스)",
        "timestamp": "2025-08-28 03:00:00"
      }
    ],
    "flo": [
      {
        "rank": 40,
        "title": "HAPPY",
        "artist": "DAY6 (데이식스)",
        "timestamp": "2025-08-28 03:00:00"
      },
      {
        "rank": 43,
        "title": "한 페이지가 될 수 있게",
        "artist": "DAY6 (데이식스)",
        "timestamp": "2025-08-28 03:00:00"
      },
      {
        "rank": 71,
        "title": "Welcome to the Show",
        "artist": "DAY6 (데이식스)",
        "timestamp": "2025-08-28 03:00:00"
      }
    ]
  },
  "2025-08-28 04:00:00": {
    "_processed_at": "2025-08-28T04:16:33.402684",
    "melon_top100": [
      {
        "rank": 24,
        "title": "HAPPY",
        "artist": "DAY6 (데이식스)",
        "timestamp": "2025-08-28 04:00:00",
        "chart_type": "TOP100"
      },
      {
        "rank": 30,
        "title": "한 페이지가 될 수 있게",
        "artist": "DAY6 (데이식스)",
        "timestamp": "2025-08-28 04:00:00",
        "chart_type": "TOP100"
      },
      {
        "rank": 40,
        "title": "Welcome to the Show",
        "artist": "DAY6 (데이식스)",
        "timestamp": "2025-08-28 04:00:00",
        "chart_type": "TOP100"
      },
      {
        "rank": 45,
        "title": "예뻤어",
        "artist": "DAY6 (데이식스)",
        "timestamp": "2025-08-28 04:00:00",
        "chart_type": "TOP100"
      }
    ],
    "melon_hot100": [
      {
        "rank": null,
        "timestamp": "2025-08-28 04:00:00",
        "chart_type": "HOT100"
      }
    ],
    "melon": [
      {
        "rank": 24,
        "title": "HAPPY",
        "artist": "DAY6 (데이식스)",
        "timestamp": "2025-08-28 04:00:00",
        "chart_type": "TOP100"
      },
      {
        "rank": 30,
        "title": "한 페이지가 될 수 있게",
        "artist": "DAY6 (데이식스)",
        "timestamp": "2025-08-28 04:00:00",
        "chart_type": "TOP100"
      },
      {
        "rank": 40,
        "title": "Welcome to the Show",
        "artist": "DAY6 (데이식스)",
        "timestamp": "2025-08-28 04:00:00",
        "chart_type": "TOP100"
      },
      {
        "rank": 45,
        "title": "예뻤어",
        "artist": "DAY6 (데이식스)",
        "timestamp": "2025-08-28 04:00:00",
        "chart_type": "TOP100"
      }
    ],
    "genie": [
      {
        "rank": 45,
        "title": "HAPPY",
        "artist": "DAY6 (데이식스)",
        "timestamp": "2025-08-28 04:00:00"
      },
      {
        "rank": 53,
        "title": "한 페이지가 될 수 있게",
        "artist": "DAY6 (데이식스)",
        "timestamp": "2025-08-28 04:00:00"
      },
      {
        "rank": 63,
        "title": "예뻤어",
        "artist": "DAY6 (데이식스)",
        "timestamp": "2025-08-28 04:00:00"
      },
      {
        "rank": 68,
        "title": "Welcome to the Show",
        "artist": "DAY6 (데이식스)",
        "timestamp": "2025-08-28 04:00:00"
      }
    ],
    "bugs": [
      {
        "rank": 32,
        "title": "HAPPY",
        "artist": "DAY6 (데이식스)",
        "timestamp": "2025-08-28 04:00:00"
      },
      {
        "rank": 39,
        "title": "한 페이지가 될 수 있게",
        "artist": "DAY6 (데이식스)",
        "timestamp": "2025-08-28 04:00:00"
      },
      {
        "rank": 58,
        "title": "Maybe Tomorrow",
        "artist": "DAY6 (데이식스)",
        "timestamp": "2025-08-28 04:00:00"
      },
      {
        "rank": 59,
        "title": "Welcome to the Show",
        "artist": "DAY6 (데이식스)",
        "timestamp": "2025-08-28 04:00:00"
      },
      {
        "rank": 73,
        "title": "Congratulations",
        "artist": "DAY6 (데이식스)",
        "timestamp": "2025-08-28 04:00:00"
      },
      {
        "rank": 80,
        "title": "예뻤어",
        "artist": "DAY6 (데이식스)",
        "timestamp": "2025-08-28 04:00:00"
      },
      {
        "rank": 89,
        "title": "녹아내려요",
        "artist": "DAY6 (데이식스)",
        "timestamp": "2025-08-28 04:00:00"
      },
      {
        "rank": 95,
        "title": "Love me or Leave me",
        "artist": "DAY6 (데이식스)",
        "timestamp": "2025-08-28 04:00:00"
      }
    ],
    "vibe": [
      {
        "rank": 30,
        "title": "HAPPY",
        "artist": "DAY6(데이식스)",
        "timestamp": "2025-08-28 04:00:00"
      },
      {
        "rank": 32,
        "title": "한 페이지가 될 수 있게",
        "artist": "DAY6(데이식스)",
        "timestamp": "2025-08-28 04:00:00"
      },
      {
        "rank": 56,
        "title": "Welcome to the Show",
        "artist": "DAY6(데이식스)",
        "timestamp": "2025-08-28 04:00:00"
      },
      {
        "rank": 67,
        "title": "예뻤어",
        "artist": "DAY6(데이식스)",
        "timestamp": "2025-08-28 04:00:00"
      }
    ],
    "flo": [
      {
        "rank": 41,
        "title": "HAPPY",
        "artist": "DAY6 (데이식스)",
        "timestamp": "2025-08-28 04:00:00"
      },
      {
        "rank": 43,
        "title": "한 페이지가 될 수 있게",
        "artist": "DAY6 (데이식스)",
        "timestamp": "2025-08-28 04:00:00"
      },
      {
        "rank": 72,
        "title": "Welcome to the Show",
        "artist": "DAY6 (데이식스)",
        "timestamp": "2025-08-28 04:00:00"
      }
    ]
  },
  "2025-08-28 05:00:00": {
    "_processed_at": "2025-08-28T05:21:56.384711",
    "melon_top100": [
      {
        "rank": 24,
        "title": "HAPPY",
        "artist": "DAY6 (데이식스)",
        "timestamp": "2025-08-28 05:00:00",
        "chart_type": "TOP100"
      },
      {
        "rank": 30,
        "title": "한 페이지가 될 수 있게",
        "artist": "DAY6 (데이식스)",
        "timestamp": "2025-08-28 05:00:00",
        "chart_type": "TOP100"
      },
      {
        "rank": 40,
        "title": "Welcome to the Show",
        "artist": "DAY6 (데이식스)",
        "timestamp": "2025-08-28 05:00:00",
        "chart_type": "TOP100"
      },
      {
        "rank": 45,
        "title": "예뻤어",
        "artist": "DAY6 (데이식스)",
        "timestamp": "2025-08-28 05:00:00",
        "chart_type": "TOP100"
      }
    ],
    "melon_hot100": [
      {
        "rank": null,
        "timestamp": "2025-08-28 05:00:00",
        "chart_type": "HOT100"
      }
    ],
    "melon": [
      {
        "rank": 24,
        "title": "HAPPY",
        "artist": "DAY6 (데이식스)",
        "timestamp": "2025-08-28 05:00:00",
        "chart_type": "TOP100"
      },
      {
        "rank": 30,
        "title": "한 페이지가 될 수 있게",
        "artist": "DAY6 (데이식스)",
        "timestamp": "2025-08-28 05:00:00",
        "chart_type": "TOP100"
      },
      {
        "rank": 40,
        "title": "Welcome to the Show",
        "artist": "DAY6 (데이식스)",
        "timestamp": "2025-08-28 05:00:00",
        "chart_type": "TOP100"
      },
      {
        "rank": 45,
        "title": "예뻤어",
        "artist": "DAY6 (데이식스)",
        "timestamp": "2025-08-28 05:00:00",
        "chart_type": "TOP100"
      }
    ],
    "genie": [
      {
        "rank": 45,
        "title": "HAPPY",
        "artist": "DAY6 (데이식스)",
        "timestamp": "2025-08-28 05:00:00"
      },
      {
        "rank": 53,
        "title": "한 페이지가 될 수 있게",
        "artist": "DAY6 (데이식스)",
        "timestamp": "2025-08-28 05:00:00"
      },
      {
        "rank": 63,
        "title": "예뻤어",
        "artist": "DAY6 (데이식스)",
        "timestamp": "2025-08-28 05:00:00"
      },
      {
        "rank": 68,
        "title": "Welcome to the Show",
        "artist": "DAY6 (데이식스)",
        "timestamp": "2025-08-28 05:00:00"
      }
    ],
    "bugs": [
      {
        "rank": 32,
        "title": "HAPPY",
        "artist": "DAY6 (데이식스)",
        "timestamp": "2025-08-28 05:00:00"
      },
      {
        "rank": 39,
        "title": "한 페이지가 될 수 있게",
        "artist": "DAY6 (데이식스)",
        "timestamp": "2025-08-28 05:00:00"
      },
      {
        "rank": 58,
        "title": "Maybe Tomorrow",
        "artist": "DAY6 (데이식스)",
        "timestamp": "2025-08-28 05:00:00"
      },
      {
        "rank": 59,
        "title": "Welcome to the Show",
        "artist": "DAY6 (데이식스)",
        "timestamp": "2025-08-28 05:00:00"
      },
      {
        "rank": 73,
        "title": "Congratulations",
        "artist": "DAY6 (데이식스)",
        "timestamp": "2025-08-28 05:00:00"
      },
      {
        "rank": 80,
        "title": "예뻤어",
        "artist": "DAY6 (데이식스)",
        "timestamp": "2025-08-28 05:00:00"
      },
      {
        "rank": 89,
        "title": "녹아내려요",
        "artist": "DAY6 (데이식스)",
        "timestamp": "2025-08-28 05:00:00"
      },
      {
        "rank": 95,
        "title": "Love me or Leave me",
        "artist": "DAY6 (데이식스)",
        "timestamp": "2025-08-28 05:00:00"
      }
    ],
    "vibe": [
      {
        "rank": 30,
        "title": "HAPPY",
        "artist": "DAY6(데이식스)",
        "timestamp": "2025-08-28 05:00:00"
      },
      {
        "rank": 32,
        "title": "한 페이지가 될 수 있게",
        "artist": "DAY6(데이식스)",
        "timestamp": "2025-08-28 05:00:00"
      },
      {
        "rank": 56,
        "title": "Welcome to the Show",
        "artist": "DAY6(데이식스)",
        "timestamp": "2025-08-28 05:00:00"
      },
      {
        "rank": 67,
        "title": "예뻤어",
        "artist": "DAY6(데이식스)",
        "timestamp": "2025-08-28 05:00:00"
      }
    ],
    "flo": [
      {
        "rank": 41,
        "title": "HAPPY",
        "artist": "DAY6 (데이식스)",
        "timestamp": "2025-08-28 05:00:00"
      },
      {
        "rank": 50,
        "title": "한 페이지가 될 수 있게",
        "artist": "DAY6 (데이식스)",
        "timestamp": "2025-08-28 05:00:00"
      },
      {
        "rank": 81,
        "title": "Welcome to the Show",
        "artist": "DAY6 (데이식스)",
        "timestamp": "2025-08-28 05:00:00"
      }
    ]
  },
  "2025-08-28 06:00:00": {
    "_processed_at": "2025-08-28T06:18:10.707577",
    "melon_top100": [
      {
        "rank": 24,
        "title": "HAPPY",
        "artist": "DAY6 (데이식스)",
        "timestamp": "2025-08-28 06:00:00",
        "chart_type": "TOP100"
      },
      {
        "rank": 30,
        "title": "한 페이지가 될 수 있게",
        "artist": "DAY6 (데이식스)",
        "timestamp": "2025-08-28 06:00:00",
        "chart_type": "TOP100"
      },
      {
        "rank": 40,
        "title": "Welcome to the Show",
        "artist": "DAY6 (데이식스)",
        "timestamp": "2025-08-28 06:00:00",
        "chart_type": "TOP100"
      },
      {
        "rank": 45,
        "title": "예뻤어",
        "artist": "DAY6 (데이식스)",
        "timestamp": "2025-08-28 06:00:00",
        "chart_type": "TOP100"
      }
    ],
    "melon_hot100": [
      {
        "rank": null,
        "timestamp": "2025-08-28 06:00:00",
        "chart_type": "HOT100"
      }
    ],
    "melon": [
      {
        "rank": 24,
        "title": "HAPPY",
        "artist": "DAY6 (데이식스)",
        "timestamp": "2025-08-28 06:00:00",
        "chart_type": "TOP100"
      },
      {
        "rank": 30,
        "title": "한 페이지가 될 수 있게",
        "artist": "DAY6 (데이식스)",
        "timestamp": "2025-08-28 06:00:00",
        "chart_type": "TOP100"
      },
      {
        "rank": 40,
        "title": "Welcome to the Show",
        "artist": "DAY6 (데이식스)",
        "timestamp": "2025-08-28 06:00:00",
        "chart_type": "TOP100"
      },
      {
        "rank": 45,
        "title": "예뻤어",
        "artist": "DAY6 (데이식스)",
        "timestamp": "2025-08-28 06:00:00",
        "chart_type": "TOP100"
      }
    ],
    "genie": [
      {
        "rank": 45,
        "title": "HAPPY",
        "artist": "DAY6 (데이식스)",
        "timestamp": "2025-08-28 06:00:00"
      },
      {
        "rank": 53,
        "title": "한 페이지가 될 수 있게",
        "artist": "DAY6 (데이식스)",
        "timestamp": "2025-08-28 06:00:00"
      },
      {
        "rank": 63,
        "title": "예뻤어",
        "artist": "DAY6 (데이식스)",
        "timestamp": "2025-08-28 06:00:00"
      },
      {
        "rank": 68,
        "title": "Welcome to the Show",
        "artist": "DAY6 (데이식스)",
        "timestamp": "2025-08-28 06:00:00"
      }
    ],
    "bugs": [
      {
        "rank": 32,
        "title": "HAPPY",
        "artist": "DAY6 (데이식스)",
        "timestamp": "2025-08-28 06:00:00"
      },
      {
        "rank": 39,
        "title": "한 페이지가 될 수 있게",
        "artist": "DAY6 (데이식스)",
        "timestamp": "2025-08-28 06:00:00"
      },
      {
        "rank": 58,
        "title": "Maybe Tomorrow",
        "artist": "DAY6 (데이식스)",
        "timestamp": "2025-08-28 06:00:00"
      },
      {
        "rank": 59,
        "title": "Welcome to the Show",
        "artist": "DAY6 (데이식스)",
        "timestamp": "2025-08-28 06:00:00"
      },
      {
        "rank": 73,
        "title": "Congratulations",
        "artist": "DAY6 (데이식스)",
        "timestamp": "2025-08-28 06:00:00"
      },
      {
        "rank": 80,
        "title": "예뻤어",
        "artist": "DAY6 (데이식스)",
        "timestamp": "2025-08-28 06:00:00"
      },
      {
        "rank": 89,
        "title": "녹아내려요",
        "artist": "DAY6 (데이식스)",
        "timestamp": "2025-08-28 06:00:00"
      },
      {
        "rank": 95,
        "title": "Love me or Leave me",
        "artist": "DAY6 (데이식스)",
        "timestamp": "2025-08-28 06:00:00"
      }
    ],
    "vibe": [
      {
        "rank": 30,
        "title": "HAPPY",
        "artist": "DAY6(데이식스)",
        "timestamp": "2025-08-28 06:00:00"
      },
      {
        "rank": 32,
        "title": "한 페이지가 될 수 있게",
        "artist": "DAY6(데이식스)",
        "timestamp": "2025-08-28 06:00:00"
      },
      {
        "rank": 56,
        "title": "Welcome to the Show",
        "artist": "DAY6(데이식스)",
        "timestamp": "2025-08-28 06:00:00"
      },
      {
        "rank": 67,
        "title": "예뻤어",
        "artist": "DAY6(데이식스)",
        "timestamp": "2025-08-28 06:00:00"
      }
    ],
    "flo": [
      {
        "rank": 47,
        "title": "HAPPY",
        "artist": "DAY6 (데이식스)",
        "timestamp": "2025-08-28 06:00:00"
      },
      {
        "rank": 51,
        "title": "한 페이지가 될 수 있게",
        "artist": "DAY6 (데이식스)",
        "timestamp": "2025-08-28 06:00:00"
      },
      {
        "rank": 82,
        "title": "Welcome to the Show",
        "artist": "DAY6 (데이식스)",
        "timestamp": "2025-08-28 06:00:00"
      }
    ]
  },
  "2025-08-28 07:00:00": {
    "_processed_at": "2025-08-28T07:18:11.639313",
    "melon_top100": [
      {
        "rank": 24,
        "title": "HAPPY",
        "artist": "DAY6 (데이식스)",
        "timestamp": "2025-08-28 07:00:00",
        "chart_type": "TOP100"
      },
      {
        "rank": 30,
        "title": "한 페이지가 될 수 있게",
        "artist": "DAY6 (데이식스)",
        "timestamp": "2025-08-28 07:00:00",
        "chart_type": "TOP100"
      },
      {
        "rank": 40,
        "title": "Welcome to the Show",
        "artist": "DAY6 (데이식스)",
        "timestamp": "2025-08-28 07:00:00",
        "chart_type": "TOP100"
      },
      {
        "rank": 45,
        "title": "예뻤어",
        "artist": "DAY6 (데이식스)",
        "timestamp": "2025-08-28 07:00:00",
        "chart_type": "TOP100"
      }
    ],
    "melon_hot100": [
      {
        "rank": null,
        "timestamp": "2025-08-28 07:00:00",
        "chart_type": "HOT100"
      }
    ],
    "melon": [
      {
        "rank": 24,
        "title": "HAPPY",
        "artist": "DAY6 (데이식스)",
        "timestamp": "2025-08-28 07:00:00",
        "chart_type": "TOP100"
      },
      {
        "rank": 30,
        "title": "한 페이지가 될 수 있게",
        "artist": "DAY6 (데이식스)",
        "timestamp": "2025-08-28 07:00:00",
        "chart_type": "TOP100"
      },
      {
        "rank": 40,
        "title": "Welcome to the Show",
        "artist": "DAY6 (데이식스)",
        "timestamp": "2025-08-28 07:00:00",
        "chart_type": "TOP100"
      },
      {
        "rank": 45,
        "title": "예뻤어",
        "artist": "DAY6 (데이식스)",
        "timestamp": "2025-08-28 07:00:00",
        "chart_type": "TOP100"
      }
    ],
    "genie": [
      {
        "rank": 36,
        "title": "HAPPY",
        "artist": "DAY6 (데이식스)",
        "timestamp": "2025-08-28 07:00:00"
      },
      {
        "rank": 45,
        "title": "한 페이지가 될 수 있게",
        "artist": "DAY6 (데이식스)",
        "timestamp": "2025-08-28 07:00:00"
      },
      {
        "rank": 63,
        "title": "Welcome to the Show",
        "artist": "DAY6 (데이식스)",
        "timestamp": "2025-08-28 07:00:00"
      },
      {
        "rank": 66,
        "title": "예뻤어",
        "artist": "DAY6 (데이식스)",
        "timestamp": "2025-08-28 07:00:00"
      }
    ],
    "bugs": [
      {
        "rank": 31,
        "title": "HAPPY",
        "artist": "DAY6 (데이식스)",
        "timestamp": "2025-08-28 07:00:00"
      },
      {
        "rank": 38,
        "title": "한 페이지가 될 수 있게",
        "artist": "DAY6 (데이식스)",
        "timestamp": "2025-08-28 07:00:00"
      },
      {
        "rank": 58,
        "title": "Welcome to the Show",
        "artist": "DAY6 (데이식스)",
        "timestamp": "2025-08-28 07:00:00"
      },
      {
        "rank": 69,
        "title": "Maybe Tomorrow",
        "artist": "DAY6 (데이식스)",
        "timestamp": "2025-08-28 07:00:00"
      },
      {
        "rank": 75,
        "title": "녹아내려요",
        "artist": "DAY6 (데이식스)",
        "timestamp": "2025-08-28 07:00:00"
      },
      {
        "rank": 81,
        "title": "Congratulations",
        "artist": "DAY6 (데이식스)",
        "timestamp": "2025-08-28 07:00:00"
      },
      {
        "rank": 89,
        "title": "예뻤어",
        "artist": "DAY6 (데이식스)",
        "timestamp": "2025-08-28 07:00:00"
      },
      {
        "rank": 96,
        "title": "Love me or Leave me",
        "artist": "DAY6 (데이식스)",
        "timestamp": "2025-08-28 07:00:00"
      }
    ],
    "vibe": [
      {
        "rank": 31,
        "title": "HAPPY",
        "artist": "DAY6(데이식스)",
        "timestamp": "2025-08-28 07:00:00"
      },
      {
        "rank": 32,
        "title": "한 페이지가 될 수 있게",
        "artist": "DAY6(데이식스)",
        "timestamp": "2025-08-28 07:00:00"
      },
      {
        "rank": 56,
        "title": "Welcome to the Show",
        "artist": "DAY6(데이식스)",
        "timestamp": "2025-08-28 07:00:00"
      },
      {
        "rank": 67,
        "title": "예뻤어",
        "artist": "DAY6(데이식스)",
        "timestamp": "2025-08-28 07:00:00"
      }
    ],
    "flo": [
      {
        "rank": 47,
        "title": "HAPPY",
        "artist": "DAY6 (데이식스)",
        "timestamp": "2025-08-28 07:00:00"
      },
      {
        "rank": 50,
        "title": "한 페이지가 될 수 있게",
        "artist": "DAY6 (데이식스)",
        "timestamp": "2025-08-28 07:00:00"
      },
      {
        "rank": 83,
        "title": "Welcome to the Show",
        "artist": "DAY6 (데이식스)",
        "timestamp": "2025-08-28 07:00:00"
      }
    ]
  },
  "2025-08-28 08:00:00": {
    "_processed_at": "2025-08-28T08:18:02.353109",
    "melon_top100": [
      {
        "rank": 23,
        "title": "HAPPY",
        "artist": "DAY6 (데이식스)",
        "timestamp": "2025-08-28 08:00:00",
        "chart_type": "TOP100"
      },
      {
        "rank": 34,
        "title": "한 페이지가 될 수 있게",
        "artist": "DAY6 (데이식스)",
        "timestamp": "2025-08-28 08:00:00",
        "chart_type": "TOP100"
      },
      {
        "rank": 43,
        "title": "Welcome to the Show",
        "artist": "DAY6 (데이식스)",
        "timestamp": "2025-08-28 08:00:00",
        "chart_type": "TOP100"
      },
      {
        "rank": 50,
        "title": "예뻤어",
        "artist": "DAY6 (데이식스)",
        "timestamp": "2025-08-28 08:00:00",
        "chart_type": "TOP100"
      }
    ],
    "melon_hot100": [
      {
        "rank": null,
        "timestamp": "2025-08-28 08:00:00",
        "chart_type": "HOT100"
      }
    ],
    "melon": [
      {
        "rank": 23,
        "title": "HAPPY",
        "artist": "DAY6 (데이식스)",
        "timestamp": "2025-08-28 08:00:00",
        "chart_type": "TOP100"
      },
      {
        "rank": 34,
        "title": "한 페이지가 될 수 있게",
        "artist": "DAY6 (데이식스)",
        "timestamp": "2025-08-28 08:00:00",
        "chart_type": "TOP100"
      },
      {
        "rank": 43,
        "title": "Welcome to the Show",
        "artist": "DAY6 (데이식스)",
        "timestamp": "2025-08-28 08:00:00",
        "chart_type": "TOP100"
      },
      {
        "rank": 50,
        "title": "예뻤어",
        "artist": "DAY6 (데이식스)",
        "timestamp": "2025-08-28 08:00:00",
        "chart_type": "TOP100"
      }
    ],
    "genie": [
      {
        "rank": 23,
        "title": "HAPPY",
        "artist": "DAY6 (데이식스)",
        "timestamp": "2025-08-28 08:00:00"
      },
      {
        "rank": 41,
        "title": "한 페이지가 될 수 있게",
        "artist": "DAY6 (데이식스)",
        "timestamp": "2025-08-28 08:00:00"
      },
      {
        "rank": 47,
        "title": "Welcome to the Show",
        "artist": "DAY6 (데이식스)",
        "timestamp": "2025-08-28 08:00:00"
      },
      {
        "rank": 55,
        "title": "예뻤어",
        "artist": "DAY6 (데이식스)",
        "timestamp": "2025-08-28 08:00:00"
      }
    ],
    "bugs": [
      {
        "rank": 26,
        "title": "HAPPY",
        "artist": "DAY6 (데이식스)",
        "timestamp": "2025-08-28 08:00:00"
      },
      {
        "rank": 33,
        "title": "한 페이지가 될 수 있게",
        "artist": "DAY6 (데이식스)",
        "timestamp": "2025-08-28 08:00:00"
      },
      {
        "rank": 39,
        "title": "Welcome to the Show",
        "artist": "DAY6 (데이식스)",
        "timestamp": "2025-08-28 08:00:00"
      },
      {
        "rank": 62,
        "title": "Maybe Tomorrow",
        "artist": "DAY6 (데이식스)",
        "timestamp": "2025-08-28 08:00:00"
      },
      {
        "rank": 71,
        "title": "Love me or Leave me",
        "artist": "DAY6 (데이식스)",
        "timestamp": "2025-08-28 08:00:00"
      },
      {
        "rank": 76,
        "title": "예뻤어",
        "artist": "DAY6 (데이식스)",
        "timestamp": "2025-08-28 08:00:00"
      },
      {
        "rank": 83,
        "title": "Congratulations",
        "artist": "DAY6 (데이식스)",
        "timestamp": "2025-08-28 08:00:00"
      },
      {
        "rank": 86,
        "title": "녹아내려요",
        "artist": "DAY6 (데이식스)",
        "timestamp": "2025-08-28 08:00:00"
      }
    ],
    "vibe": [
      {
        "rank": 31,
        "title": "HAPPY",
        "artist": "DAY6(데이식스)",
        "timestamp": "2025-08-28 08:00:00"
      },
      {
        "rank": 32,
        "title": "한 페이지가 될 수 있게",
        "artist": "DAY6(데이식스)",
        "timestamp": "2025-08-28 08:00:00"
      },
      {
        "rank": 56,
        "title": "Welcome to the Show",
        "artist": "DAY6(데이식스)",
        "timestamp": "2025-08-28 08:00:00"
      },
      {
        "rank": 67,
        "title": "예뻤어",
        "artist": "DAY6(데이식스)",
        "timestamp": "2025-08-28 08:00:00"
      }
    ],
    "flo": [
      {
        "rank": 47,
        "title": "HAPPY",
        "artist": "DAY6 (데이식스)",
        "timestamp": "2025-08-28 08:00:00"
      },
      {
        "rank": 50,
        "title": "한 페이지가 될 수 있게",
        "artist": "DAY6 (데이식스)",
        "timestamp": "2025-08-28 08:00:00"
      },
      {
        "rank": 78,
        "title": "Welcome to the Show",
        "artist": "DAY6 (데이식스)",
        "timestamp": "2025-08-28 08:00:00"
      }
    ]
  },
  "2025-08-28 10:00:00": {
    "_processed_at": "2025-08-28T10:28:14.786131",
    "melon_top100": [
      {
        "rank": 27,
        "title": "HAPPY",
        "artist": "DAY6 (데이식스)",
        "timestamp": "2025-08-28 10:00:00",
        "chart_type": "TOP100"
      },
      {
        "rank": 33,
        "title": "한 페이지가 될 수 있게",
        "artist": "DAY6 (데이식스)",
        "timestamp": "2025-08-28 10:00:00",
        "chart_type": "TOP100"
      },
      {
        "rank": 47,
        "title": "Welcome to the Show",
        "artist": "DAY6 (데이식스)",
        "timestamp": "2025-08-28 10:00:00",
        "chart_type": "TOP100"
      },
      {
        "rank": 51,
        "title": "예뻤어",
        "artist": "DAY6 (데이식스)",
        "timestamp": "2025-08-28 10:00:00",
        "chart_type": "TOP100"
      }
    ],
    "melon_hot100": [
      {
        "rank": null,
        "timestamp": "2025-08-28 10:00:00",
        "chart_type": "HOT100"
      }
    ],
    "melon": [
      {
        "rank": 27,
        "title": "HAPPY",
        "artist": "DAY6 (데이식스)",
        "timestamp": "2025-08-28 10:00:00",
        "chart_type": "TOP100"
      },
      {
        "rank": 33,
        "title": "한 페이지가 될 수 있게",
        "artist": "DAY6 (데이식스)",
        "timestamp": "2025-08-28 10:00:00",
        "chart_type": "TOP100"
      },
      {
        "rank": 47,
        "title": "Welcome to the Show",
        "artist": "DAY6 (데이식스)",
        "timestamp": "2025-08-28 10:00:00",
        "chart_type": "TOP100"
      },
      {
        "rank": 51,
        "title": "예뻤어",
        "artist": "DAY6 (데이식스)",
        "timestamp": "2025-08-28 10:00:00",
        "chart_type": "TOP100"
      }
    ],
    "genie": [
      {
        "rank": 21,
        "title": "HAPPY",
        "artist": "DAY6 (데이식스)",
        "timestamp": "2025-08-28 10:00:00"
      },
      {
        "rank": 33,
        "title": "한 페이지가 될 수 있게",
        "artist": "DAY6 (데이식스)",
        "timestamp": "2025-08-28 10:00:00"
      },
      {
        "rank": 50,
        "title": "Welcome to the Show",
        "artist": "DAY6 (데이식스)",
        "timestamp": "2025-08-28 10:00:00"
      },
      {
        "rank": 54,
        "title": "예뻤어",
        "artist": "DAY6 (데이식스)",
        "timestamp": "2025-08-28 10:00:00"
      }
    ],
    "bugs": [
      {
        "rank": 30,
        "title": "HAPPY",
        "artist": "DAY6 (데이식스)",
        "timestamp": "2025-08-28 10:00:00"
      },
      {
        "rank": 36,
        "title": "한 페이지가 될 수 있게",
        "artist": "DAY6 (데이식스)",
        "timestamp": "2025-08-28 10:00:00"
      },
      {
        "rank": 52,
        "title": "Welcome to the Show",
        "artist": "DAY6 (데이식스)",
        "timestamp": "2025-08-28 10:00:00"
      },
      {
        "rank": 59,
        "title": "Maybe Tomorrow",
        "artist": "DAY6 (데이식스)",
        "timestamp": "2025-08-28 10:00:00"
      },
      {
        "rank": 61,
        "title": "예뻤어",
        "artist": "DAY6 (데이식스)",
        "timestamp": "2025-08-28 10:00:00"
      },
      {
        "rank": 81,
        "title": "Love me or Leave me",
        "artist": "DAY6 (데이식스)",
        "timestamp": "2025-08-28 10:00:00"
      },
      {
        "rank": 87,
        "title": "Congratulations",
        "artist": "DAY6 (데이식스)",
        "timestamp": "2025-08-28 10:00:00"
      },
      {
        "rank": 88,
        "title": "녹아내려요",
        "artist": "DAY6 (데이식스)",
        "timestamp": "2025-08-28 10:00:00"
      }
    ],
    "vibe": [
      {
        "rank": 31,
        "title": "HAPPY",
        "artist": "DAY6(데이식스)",
        "timestamp": "2025-08-28 10:00:00"
      },
      {
        "rank": 32,
        "title": "한 페이지가 될 수 있게",
        "artist": "DAY6(데이식스)",
        "timestamp": "2025-08-28 10:00:00"
      },
      {
        "rank": 56,
        "title": "Welcome to the Show",
        "artist": "DAY6(데이식스)",
        "timestamp": "2025-08-28 10:00:00"
      },
      {
        "rank": 67,
        "title": "예뻤어",
        "artist": "DAY6(데이식스)",
        "timestamp": "2025-08-28 10:00:00"
      }
    ],
    "flo": [
      {
        "rank": 40,
        "title": "HAPPY",
        "artist": "DAY6 (데이식스)",
        "timestamp": "2025-08-28 10:00:00"
      },
      {
        "rank": 43,
        "title": "한 페이지가 될 수 있게",
        "artist": "DAY6 (데이식스)",
        "timestamp": "2025-08-28 10:00:00"
      },
      {
        "rank": 70,
        "title": "Welcome to the Show",
        "artist": "DAY6 (데이식스)",
        "timestamp": "2025-08-28 10:00:00"
      }
    ]
  },
  "2025-08-28 12:00:00": {
    "_processed_at": "2025-08-28T12:02:41.336680",
    "melon_top100": [
      {
        "rank": 27,
        "title": "HAPPY",
        "artist": "DAY6 (데이식스)",
        "timestamp": "2025-08-28 12:00:00",
        "chart_type": "TOP100"
      },
      {
        "rank": 31,
        "title": "한 페이지가 될 수 있게",
        "artist": "DAY6 (데이식스)",
        "timestamp": "2025-08-28 12:00:00",
        "chart_type": "TOP100"
      },
      {
        "rank": 43,
        "title": "Welcome to the Show",
        "artist": "DAY6 (데이식스)",
        "timestamp": "2025-08-28 12:00:00",
        "chart_type": "TOP100"
      },
      {
        "rank": 47,
        "title": "예뻤어",
        "artist": "DAY6 (데이식스)",
        "timestamp": "2025-08-28 12:00:00",
        "chart_type": "TOP100"
      }
    ],
    "melon_hot100": [
      {
        "rank": null,
        "timestamp": "2025-08-28 12:00:00",
        "chart_type": "HOT100"
      }
    ],
    "melon": [
      {
        "rank": 27,
        "title": "HAPPY",
        "artist": "DAY6 (데이식스)",
        "timestamp": "2025-08-28 12:00:00",
        "chart_type": "TOP100"
      },
      {
        "rank": 31,
        "title": "한 페이지가 될 수 있게",
        "artist": "DAY6 (데이식스)",
        "timestamp": "2025-08-28 12:00:00",
        "chart_type": "TOP100"
      },
      {
        "rank": 43,
        "title": "Welcome to the Show",
        "artist": "DAY6 (데이식스)",
        "timestamp": "2025-08-28 12:00:00",
        "chart_type": "TOP100"
      },
      {
        "rank": 47,
        "title": "예뻤어",
        "artist": "DAY6 (데이식스)",
        "timestamp": "2025-08-28 12:00:00",
        "chart_type": "TOP100"
      }
    ],
    "genie": [
      {
        "rank": 21,
        "title": "HAPPY",
        "artist": "DAY6 (데이식스)",
        "timestamp": "2025-08-28 12:00:00"
      },
      {
        "rank": 27,
        "title": "한 페이지가 될 수 있게",
        "artist": "DAY6 (데이식스)",
        "timestamp": "2025-08-28 12:00:00"
      },
      {
        "rank": 37,
        "title": "Welcome to the Show",
        "artist": "DAY6 (데이식스)",
        "timestamp": "2025-08-28 12:00:00"
      },
      {
        "rank": 49,
        "title": "예뻤어",
        "artist": "DAY6 (데이식스)",
        "timestamp": "2025-08-28 12:00:00"
      }
    ],
    "bugs": [
      {
        "rank": 36,
        "title": "한 페이지가 될 수 있게",
        "artist": "DAY6 (데이식스)",
        "timestamp": "2025-08-28 12:00:00"
      },
      {
        "rank": 37,
        "title": "HAPPY",
        "artist": "DAY6 (데이식스)",
        "timestamp": "2025-08-28 12:00:00"
      },
      {
        "rank": 42,
        "title": "Welcome to the Show",
        "artist": "DAY6 (데이식스)",
        "timestamp": "2025-08-28 12:00:00"
      },
      {
        "rank": 62,
        "title": "Maybe Tomorrow",
        "artist": "DAY6 (데이식스)",
        "timestamp": "2025-08-28 12:00:00"
      },
      {
        "rank": 70,
        "title": "예뻤어",
        "artist": "DAY6 (데이식스)",
        "timestamp": "2025-08-28 12:00:00"
      },
      {
        "rank": 84,
        "title": "Congratulations",
        "artist": "DAY6 (데이식스)",
        "timestamp": "2025-08-28 12:00:00"
      },
      {
        "rank": 87,
        "title": "녹아내려요",
        "artist": "DAY6 (데이식스)",
        "timestamp": "2025-08-28 12:00:00"
      },
      {
        "rank": 91,
        "title": "Love me or Leave me",
        "artist": "DAY6 (데이식스)",
        "timestamp": "2025-08-28 12:00:00"
      }
    ],
    "vibe": [
      {
        "rank": 31,
        "title": "HAPPY",
        "artist": "DAY6(데이식스)",
        "timestamp": "2025-08-28 12:00:00"
      },
      {
        "rank": 32,
        "title": "한 페이지가 될 수 있게",
        "artist": "DAY6(데이식스)",
        "timestamp": "2025-08-28 12:00:00"
      },
      {
        "rank": 56,
        "title": "Welcome to the Show",
        "artist": "DAY6(데이식스)",
        "timestamp": "2025-08-28 12:00:00"
      },
      {
        "rank": 67,
        "title": "예뻤어",
        "artist": "DAY6(데이식스)",
        "timestamp": "2025-08-28 12:00:00"
      }
    ],
    "flo": [
      {
        "rank": 40,
        "title": "HAPPY",
        "artist": "DAY6 (데이식스)",
        "timestamp": "2025-08-28 12:00:00"
      },
      {
        "rank": 42,
        "title": "한 페이지가 될 수 있게",
        "artist": "DAY6 (데이식스)",
        "timestamp": "2025-08-28 12:00:00"
      },
      {
        "rank": 69,
        "title": "Welcome to the Show",
        "artist": "DAY6 (데이식스)",
        "timestamp": "2025-08-28 12:00:00"
      }
    ]
  },
  "2025-08-28 13:00:00": {
    "_processed_at": "2025-08-28T13:23:44.526468",
    "melon_top100": [
      {
        "rank": 25,
        "title": "HAPPY",
        "artist": "DAY6 (데이식스)",
        "timestamp": "2025-08-28 13:00:00",
        "chart_type": "TOP100"
      },
      {
        "rank": 31,
        "title": "한 페이지가 될 수 있게",
        "artist": "DAY6 (데이식스)",
        "timestamp": "2025-08-28 13:00:00",
        "chart_type": "TOP100"
      },
      {
        "rank": 44,
        "title": "Welcome to the Show",
        "artist": "DAY6 (데이식스)",
        "timestamp": "2025-08-28 13:00:00",
        "chart_type": "TOP100"
      },
      {
        "rank": 48,
        "title": "예뻤어",
        "artist": "DAY6 (데이식스)",
        "timestamp": "2025-08-28 13:00:00",
        "chart_type": "TOP100"
      }
    ],
    "melon_hot100": [
      {
        "rank": null,
        "timestamp": "2025-08-28 13:00:00",
        "chart_type": "HOT100"
      }
    ],
    "melon": [
      {
        "rank": 25,
        "title": "HAPPY",
        "artist": "DAY6 (데이식스)",
        "timestamp": "2025-08-28 13:00:00",
        "chart_type": "TOP100"
      },
      {
        "rank": 31,
        "title": "한 페이지가 될 수 있게",
        "artist": "DAY6 (데이식스)",
        "timestamp": "2025-08-28 13:00:00",
        "chart_type": "TOP100"
      },
      {
        "rank": 44,
        "title": "Welcome to the Show",
        "artist": "DAY6 (데이식스)",
        "timestamp": "2025-08-28 13:00:00",
        "chart_type": "TOP100"
      },
      {
        "rank": 48,
        "title": "예뻤어",
        "artist": "DAY6 (데이식스)",
        "timestamp": "2025-08-28 13:00:00",
        "chart_type": "TOP100"
      }
    ],
    "genie": [
      {
        "rank": 20,
        "title": "HAPPY",
        "artist": "DAY6 (데이식스)",
        "timestamp": "2025-08-28 13:00:00"
      },
      {
        "rank": 23,
        "title": "한 페이지가 될 수 있게",
        "artist": "DAY6 (데이식스)",
        "timestamp": "2025-08-28 13:00:00"
      },
      {
        "rank": 39,
        "title": "예뻤어",
        "artist": "DAY6 (데이식스)",
        "timestamp": "2025-08-28 13:00:00"
      },
      {
        "rank": 40,
        "title": "Welcome to the Show",
        "artist": "DAY6 (데이식스)",
        "timestamp": "2025-08-28 13:00:00"
      }
    ],
    "bugs": [
      {
        "rank": 18,
        "title": "HAPPY",
        "artist": "DAY6 (데이식스)",
        "timestamp": "2025-08-28 13:00:00"
      },
      {
        "rank": 31,
        "title": "한 페이지가 될 수 있게",
        "artist": "DAY6 (데이식스)",
        "timestamp": "2025-08-28 13:00:00"
      },
      {
        "rank": 51,
        "title": "Maybe Tomorrow",
        "artist": "DAY6 (데이식스)",
        "timestamp": "2025-08-28 13:00:00"
      },
      {
        "rank": 59,
        "title": "예뻤어",
        "artist": "DAY6 (데이식스)",
        "timestamp": "2025-08-28 13:00:00"
      },
      {
        "rank": 64,
        "title": "Welcome to the Show",
        "artist": "DAY6 (데이식스)",
        "timestamp": "2025-08-28 13:00:00"
      },
      {
        "rank": 88,
        "title": "Congratulations",
        "artist": "DAY6 (데이식스)",
        "timestamp": "2025-08-28 13:00:00"
      },
      {
        "rank": 89,
        "title": "Love me or Leave me",
        "artist": "DAY6 (데이식스)",
        "timestamp": "2025-08-28 13:00:00"
      },
      {
        "rank": 93,
        "title": "녹아내려요",
        "artist": "DAY6 (데이식스)",
        "timestamp": "2025-08-28 13:00:00"
      }
    ],
    "vibe": [
      {
        "rank": 31,
        "title": "HAPPY",
        "artist": "DAY6(데이식스)",
        "timestamp": "2025-08-28 13:00:00"
      },
      {
        "rank": 32,
        "title": "한 페이지가 될 수 있게",
        "artist": "DAY6(데이식스)",
        "timestamp": "2025-08-28 13:00:00"
      },
      {
        "rank": 56,
        "title": "Welcome to the Show",
        "artist": "DAY6(데이식스)",
        "timestamp": "2025-08-28 13:00:00"
      },
      {
        "rank": 67,
        "title": "예뻤어",
        "artist": "DAY6(데이식스)",
        "timestamp": "2025-08-28 13:00:00"
      }
    ],
    "flo": [
      {
        "rank": 39,
        "title": "HAPPY",
        "artist": "DAY6 (데이식스)",
        "timestamp": "2025-08-28 13:00:00"
      },
      {
        "rank": 42,
        "title": "한 페이지가 될 수 있게",
        "artist": "DAY6 (데이식스)",
        "timestamp": "2025-08-28 13:00:00"
      },
      {
        "rank": 70,
        "title": "Welcome to the Show",
        "artist": "DAY6 (데이식스)",
        "timestamp": "2025-08-28 13:00:00"
      }
    ]
  },
  "2025-08-28 14:00:00": {
    "_processed_at": "2025-08-28T14:19:24.304543",
    "melon_top100": [
      {
        "rank": 26,
        "title": "HAPPY",
        "artist": "DAY6 (데이식스)",
        "timestamp": "2025-08-28 14:00:00",
        "chart_type": "TOP100"
      },
      {
        "rank": 32,
        "title": "한 페이지가 될 수 있게",
        "artist": "DAY6 (데이식스)",
        "timestamp": "2025-08-28 14:00:00",
        "chart_type": "TOP100"
      },
      {
        "rank": 42,
        "title": "Welcome to the Show",
        "artist": "DAY6 (데이식스)",
        "timestamp": "2025-08-28 14:00:00",
        "chart_type": "TOP100"
      },
      {
        "rank": 46,
        "title": "예뻤어",
        "artist": "DAY6 (데이식스)",
        "timestamp": "2025-08-28 14:00:00",
        "chart_type": "TOP100"
      }
    ],
    "melon_hot100": [
      {
        "rank": null,
        "timestamp": "2025-08-28 14:00:00",
        "chart_type": "HOT100"
      }
    ],
    "melon": [
      {
        "rank": 26,
        "title": "HAPPY",
        "artist": "DAY6 (데이식스)",
        "timestamp": "2025-08-28 14:00:00",
        "chart_type": "TOP100"
      },
      {
        "rank": 32,
        "title": "한 페이지가 될 수 있게",
        "artist": "DAY6 (데이식스)",
        "timestamp": "2025-08-28 14:00:00",
        "chart_type": "TOP100"
      },
      {
        "rank": 42,
        "title": "Welcome to the Show",
        "artist": "DAY6 (데이식스)",
        "timestamp": "2025-08-28 14:00:00",
        "chart_type": "TOP100"
      },
      {
        "rank": 46,
        "title": "예뻤어",
        "artist": "DAY6 (데이식스)",
        "timestamp": "2025-08-28 14:00:00",
        "chart_type": "TOP100"
      }
    ],
    "genie": [
      {
        "rank": 20,
        "title": "HAPPY",
        "artist": "DAY6 (데이식스)",
        "timestamp": "2025-08-28 14:00:00"
      },
      {
        "rank": 26,
        "title": "한 페이지가 될 수 있게",
        "artist": "DAY6 (데이식스)",
        "timestamp": "2025-08-28 14:00:00"
      },
      {
        "rank": 30,
        "title": "예뻤어",
        "artist": "DAY6 (데이식스)",
        "timestamp": "2025-08-28 14:00:00"
      },
      {
        "rank": 39,
        "title": "Welcome to the Show",
        "artist": "DAY6 (데이식스)",
        "timestamp": "2025-08-28 14:00:00"
      }
    ],
    "bugs": [
      {
        "rank": 21,
        "title": "예뻤어",
        "artist": "DAY6 (데이식스)",
        "timestamp": "2025-08-28 14:00:00"
      },
      {
        "rank": 34,
        "title": "Welcome to the Show",
        "artist": "DAY6 (데이식스)",
        "timestamp": "2025-08-28 14:00:00"
      },
      {
        "rank": 45,
        "title": "HAPPY",
        "artist": "DAY6 (데이식스)",
        "timestamp": "2025-08-28 14:00:00"
      },
      {
        "rank": 51,
        "title": "Love me or Leave me",
        "artist": "DAY6 (데이식스)",
        "timestamp": "2025-08-28 14:00:00"
      },
      {
        "rank": 53,
        "title": "한 페이지가 될 수 있게",
        "artist": "DAY6 (데이식스)",
        "timestamp": "2025-08-28 14:00:00"
      },
      {
        "rank": 71,
        "title": "Congratulations",
        "artist": "DAY6 (데이식스)",
        "timestamp": "2025-08-28 14:00:00"
      },
      {
        "rank": 75,
        "title": "Maybe Tomorrow",
        "artist": "DAY6 (데이식스)",
        "timestamp": "2025-08-28 14:00:00"
      },
      {
        "rank": 93,
        "title": "녹아내려요",
        "artist": "DAY6 (데이식스)",
        "timestamp": "2025-08-28 14:00:00"
      }
    ],
    "vibe": [
      {
        "rank": 31,
        "title": "HAPPY",
        "artist": "DAY6(데이식스)",
        "timestamp": "2025-08-28 14:00:00"
      },
      {
        "rank": 32,
        "title": "한 페이지가 될 수 있게",
        "artist": "DAY6(데이식스)",
        "timestamp": "2025-08-28 14:00:00"
      },
      {
        "rank": 56,
        "title": "Welcome to the Show",
        "artist": "DAY6(데이식스)",
        "timestamp": "2025-08-28 14:00:00"
      },
      {
        "rank": 67,
        "title": "예뻤어",
        "artist": "DAY6(데이식스)",
        "timestamp": "2025-08-28 14:00:00"
      }
    ],
    "flo": [
      {
        "rank": 39,
        "title": "HAPPY",
        "artist": "DAY6 (데이식스)",
        "timestamp": "2025-08-28 14:00:00"
      },
      {
        "rank": 41,
        "title": "한 페이지가 될 수 있게",
        "artist": "DAY6 (데이식스)",
        "timestamp": "2025-08-28 14:00:00"
      },
      {
        "rank": 69,
        "title": "Welcome to the Show",
        "artist": "DAY6 (데이식스)",
        "timestamp": "2025-08-28 14:00:00"
      }
    ]
  }
}